Workbook

Sheet Contas
A1: Contas / Carteiras
A2: Preencha aqui todas as contas que você quer controlar. Use o Nome da Conta exatamente igual na aba Lançamentos.
A4: Nome da Conta | B4: Tipo | C4: Saldo Inicial | D4: Data Saldo Inicial | E4: Observações
A5: Conta Corrente | B5: Conta Corrente | C5: 0 | D5: 2026-08-01 | E5: ex.: Banco X
A6: Cartão de Crédito | B6: Cartão de Crédito | C6: 0 | D6: 2026-08-01 | E6: ex.: fatura atual em aberto
A7: Carteira | B7: Dinheiro | C7: 0 | D7: 2026-08-01 | E7: espécie
A8: Investimentos | B8: Investimento | C8: 0 | D8: 2026-08-01 | E8: renda fixa/variável

Sheet Categorias
A1: Categorias e Subcategorias
A2: Categorias padrão sugeridas — edite, adicione ou remova livremente. Use exatamente estes nomes na aba Lançamentos e no Orçamento.
A4: Categoria | B4: Subcategoria | C4: Tipo
A5: Receita | B5: Salário | C5: Receita
A6: Receita | B6: Freelance/Extra | C6: Receita
A7: Receita | B7: Rendimentos de Investimento | C7: Receita
A8: Receita | B8: Outras Receitas | C8: Receita
A9: Moradia | B9: Aluguel/Financiamento | C9: Despesa
A10: Moradia | B10: Condomínio | C10: Despesa
A11: Moradia | B11: Água/Luz/Gás | C11: Despesa
A12: Moradia | B12: Internet/Telefone | C12: Despesa
A13: Moradia | B13: Manutenção | C13: Despesa
A14: Alimentação | B14: Supermercado | C14: Despesa
A15: Alimentação | B15: Restaurante/Delivery | C15: Despesa
... A31: Outros | B31: Diversos | C31: Despesa

Sheet Lançamentos
A1: Lançamentos
A2: Registre aqui manualmente cada movimentação. Use os menus (Conta, Categoria, Tipo) para manter consistência.
A4: Data | B4: Conta | C4: Categoria | D4: Subcategoria | E4: Tipo | F4: Descrição | G4: Valor | H4: Forma de Pagamento | I4: Parcela | J4: Status
A5: 2026-08-01 | B5: Conta Corrente | C5: Receita | D5: Salário | E5: Receita | F5: Salário mensal | G5: 5000 | H5: Transferência | J5: Pago
A6: 2026-08-03 | B6: Cartão de Crédito | C6: Alimentação | D6: Supermercado | E6: Despesa | F6: Compras do mês | G6: 450.3 | H6: Crédito | I6: 1/1 | J6: Pendente

Sheet Orçamento
A1: Orçamento Mensal — Planejado x Realizado
A2: Preencha o valor Planejado por categoria e mês (célula amarela). Realizado é calculado automaticamente a partir da aba Lançamentos.
A3: Ano de Referência: | B3: 2026
A5: Categoria | B5: Janeiro - Planejado | C5: Janeiro - Realizado | D5: Janeiro - Diferença | E5: Fevereiro - Planejado | F5: Fevereiro - Realizado | G5: Fevereiro - Diferença | H5: Março - Planejado | I5: Março - Realizado | J5: Março - Diferença | K5: Abril - Planejado | L5: Abril - Realizado | M5: Abril - Diferença | N5: Maio - Planejado | O5: Maio - Realizado | P5: Maio - Diferença | Q5: Junho - Planejado | R5: Junho - Realizado | S5: Junho - Diferença | T5: Julho - Planejado | U5: Julho - Realizado | V5: Julho - Diferença | W5: Agosto - Planejado | X5: Agosto - Realizado | Y5: Agosto - Diferença | Z5: Setembro - Planejado | AA5: Setembro - Realizado | AB5: Setembro - Diferença | AC5: Outubro - Planejado | AD5: Outubro - Realizado | AE5: Outubro - Diferença | AF5: Novembro - Planejado | AG5: Novembro - Realizado | AH5: Novembro - Diferença | AI5: Dezembro - Planejado | AJ5: Dezembro - Realizado | AK5: Dezembro - Diferença
A6: Alimentação | B6: 0 | C6: =SUMPRODUCT((Lançamentos!$C$5:$C$2000=$A6)*(Lançamentos!$E$5:$E$2000="Despesa")*(YEAR(Lançamentos!$A$5:$A$2000)=$B$3)*(MONTH(Lançamentos!$A$5:$A$2000)=1)*Lançamentos!$G$5:$G$2000) | D6: =B6-C6 | E6: 0 | F6: =SUMPRODUCT((Lançamentos!$C$5:$C$2000=$A6)*(Lançamentos!$E$5:$E$2000="Despesa")*(YEAR(Lançamentos!$A$5:$A$2000)=$B$3)*(MONTH(Lançamentos!$A$5:$A$2000)=2)*Lançamentos!$G$5:$G$2000) | G6: =E6-F6 | H6: 0 | I6: =SUMPRODUCT((Lançamentos!$C$5:$C$2000=$A6)*(Lançamentos!$E$5:$E$2000="Despesa")*(YEAR(Lançamentos!$A$5:$A$2000)=$B$3)*(MONTH(Lançamentos!$A$5:$A$2000)=3)*Lançamentos!$G$5:$G$2000) | J6: =H6-I6 | K6: 0 | L6: =SUMPRODUCT((Lançamentos!$C$5:$C$2000=$A6)*(Lançamentos!$E$5:$E$2000="Despesa")*(YEAR(Lançamentos!$A$5:$A$2000)=$B$3)*(MONTH(Lançamentos!$A$5:$A$2000)=4)*Lançamentos!$G$5:$G$2000) | M6: =K6-L6 | N6: 0 | O6: =SUMPRODUCT((Lançamentos!$C$5:$C$2000=$A6)*(Lançamentos!$E$5:$E$2000="Despesa")*(YEAR(Lançamentos!$A$5:$A$2000)=$B$3)*(MONTH(Lançamentos!$A$5:$A$2000)=5)*Lançamentos!$G$5:$G$2000) | P6: =N6-O6 | Q6: 0 | R6: =SUMPRODUCT((Lançamentos!$C$5:$C$2000=$A6)*(Lançamentos!$E$5:$E$2000="Despesa")*(YEAR(Lançamentos!$A$5:$A$2000)=$B$3)*(MONTH(Lançamentos!$A$5:$A$2000)=6)*Lançamentos!$G$5:$G$2000) | S6: =Q6-R6 | T6: 0 | U6: =SUMPRODUCT((Lançamentos!$C$5:$C$2000=$A6)*(Lançamentos!$E$5:$E$2000="Despesa")*(YEAR(Lançamentos!$A$5:$A$2000)=$B$3)*(MONTH(Lançamentos!$A$5:$A$2000)=7)*Lançamentos!$G$5:$G$2000) | V6: =T6-U6 | W6: 0 | X6: =SUMPRODUCT((Lançamentos!$C$5:$C$2000=$A6)*(Lançamentos!$E$5:$E$2000="Despesa")*(YEAR(Lançamentos!$A$5:$A$2000)=$B$3)*(MONTH(Lançamentos!$A$5:$A$2000)=8)*Lançamentos!$G$5:$G$2000) | Y6: =W6-X6 | Z6: 0 | AA6: =SUMPRODUCT((Lançamentos!$C$5:$C$2000=$A6)*(Lançamentos!$E$5:$E$2000="Despesa")*(YEAR(Lançamentos!$A$5:$A$2000)=$B$3)*(MONTH(Lançamentos!$A$5:$A$2000)=9)*Lançamentos!$G$5:$G$2000) | AB6: =Z6-AA6 | AC6: 0 | AD6: =SUMPRODUCT((Lançamentos!$C$5:$C$2000=$A6)*(Lançamentos!$E$5:$E$2000="Despesa")*(YEAR(Lançamentos!$A$5:$A$2000)=$B$3)*(MONTH(Lançamentos!$A$5:$A$2000)=10)*Lançamentos!$G$5:$G$2000) | AE6: =AC6-AD6 | AF6: 0 | AG6: =SUMPRODUCT((Lançamentos!$C$5:$C$2000=$A6)*(Lançamentos!$E$5:$E$2000="Despesa")*(YEAR(Lançamentos!$A$5:$A$2000)=$B$3)*(MONTH(Lançamentos!$A$5:$A$2000)=11)*Lançamentos!$G$5:$G$2000) | AH6: =AF6-AG6 | AI6: 0 | AJ6: =SUMPRODUCT((Lançamentos!$C$5:$C$2000=$A6)*(Lançamentos!$E$5:$E$2000="Despesa")*(YEAR(Lançamentos!$A$5:$A$2000)=$B$3)*(MONTH(Lançamentos!$A$5:$A$2000)=12)*Lançamentos!$G$5:$G$2000) | AK6: =AI6-AJ6
A7: Cartão de Crédito | B7: 0 | C7: =SUMPRODUCT((Lançamentos!$C$5:$C$2000=$A7)*(Lançamentos!$E$5:$E$2000="Despesa")*(YEAR(Lançamentos!$A$5:$A$2000)=$B$3)*(MONTH(Lançamentos!$A$5:$A$2000)=1)*Lançamentos!$G$5:$G$2000) | D7: =B7-C7 | E7: 0 | F7: =SUMPRODUCT((Lançamentos!$C$5:$C$2000=$A7)*(Lançamentos!$E$5:$E$2000="Despesa")*(YEAR(Lançamentos!$A$5:$A$2000)=$B$3)*(MONTH(Lançamentos!$A$5:$A$2000)=2)*Lançamentos!$G$5:$G$2000) | G7: =E7-F7 | H7: 0 | I7: =SUMPRODUCT((Lançamentos!$C$5:$C$2000=$A7)*(Lançamentos!$E$5:$E$2000="Despesa")*(YEAR(Lançamentos!$A$5:$A$2000)=$B$3)*(MONTH(Lançamentos!$A$5:$A$2000)=3)*Lançamentos!$G$5:$G$2000) | J7: =H7-I7 | K7: 0 | L7: =SUMPRODUCT((Lançamentos!$C$5:$C$2000=$A7)*(Lançamentos!$E$5:$E$2000="Despesa")*(YEAR(Lançamentos!$A$5:$A$2000)=$B$3)*(MONTH(Lançamentos!$A$5:$A$2000)=4)*Lançamentos!$G$5:$G$2000) | M7: =K7-L7 | N7: 0 | O7: =SUMPRODUCT((Lançamentos!$C$5:$C$2000=$A7)*(Lançamentos!$E$5:$E$2000="Despesa")*(YEAR(Lançamentos!$A$5:$A$2000)=$B$3)*(MONTH(Lançamentos!$A$5:$A$2000)=5)*Lançamentos!$G$5:$G$2000) | P7: =N7-O7 | Q7: 0 | R7: =SUMPRODUCT((Lançamentos!$C$5:$C$2000=$A7)*(Lançamentos!$E$5:$E$2000="Despesa")*(YEAR(Lançamentos!$A$5:$A$2000)=$B$3)*(MONTH(Lançamentos!$A$5:$A$2000)=6)*Lançamentos!$G$5:$G$2000) | S7: =Q7-R7 | T7: 0 | U7: =SUMPRODUCT((Lançamentos!$C$5:$C$2000=$A7)*(Lançamentos!$E$5:$E$2000="Despesa")*(YEAR(Lançamentos!$A$5:$A$2000)=$B$3)*(MONTH(Lançamentos!$A$5:$A$2000)=7)*Lançamentos!$G$5:$G$2000) | V7: =T7-U7 | W7: 0 | X7: =SUMPRODUCT((Lançamentos!$C$5:$C$2000=$A7)*(Lançamentos!$E$5:$E$2000="Despesa")*(YEAR(Lançamentos!$A$5:$A$2000)=$B$3)*(MONTH(Lançamentos!$A$5:$A$2000)=8)*Lançamentos!$G$5:$G$2000) | Y7: =W7-X7 | Z7: 0 | AA7: =SUMPRODUCT((Lançamentos!$C$5:$C$2000=$A7)*(Lançamentos!$E$5:$E$2000="Despesa")*(YEAR(Lançamentos!$A$5:$A$2000)=$B$3)*(MONTH(Lançamentos!$A$5:$A$2000)=9)*Lançamentos!$G$5:$G$2000) | AB7: =Z7-AA7 | AC7: 0 | AD7: =SUMPRODUCT((Lançamentos!$C$5:$C$2000=$A7)*(Lançamentos!$E$5:$E$2000="Despesa")*(YEAR(Lançamentos!$A$5:$A$2000)=$B$3)*(MONTH(Lançamentos!$A$5:$A$2000)=10)*Lançamentos!$G$5:$G$2000) | AE7: =AC7-AD7 | AF7: 0 | AG7: =SUMPRODUCT((Lançamentos!$C$5:$C$2000=$A7)*(Lançamentos!$E$5:$E$2000="Despesa")*(YEAR(Lançamentos!$A$5:$A$2000)=$B$3)*(MONTH(Lançamentos!$A$5:$A$2000)=11)*Lançamentos!$G$5:$G$2000) | AH7: =AF7-AG7 | AI7: 0 | AJ7: =SUMPRODUCT((Lançamentos!$C$5:$C$2000=$A7)*(Lançamentos!$E$5:$E$2000="Despesa")*(YEAR(Lançamentos!$A$5:$A$2000)=$B$3)*(MONTH(Lançamentos!$A$5:$A$2000)=12)*Lançamentos!$G$5:$G$2000) | AK7: =AI7-AJ7
A8: Dívidas | B8: 0 | C8: =SUMPRODUCT((Lançamentos!$C$5:$C$2000=$A8)*(Lançamentos!$E$5:$E$2000="Despesa")*(YEAR(Lançamentos!$A$5:$A$2000)=$B$3)*(MONTH(Lançamentos!$A$5:$A$2000)=1)*Lançamentos!$G$5:$G$2000) | D8: =B8-C8 | E8: 0 | F8: =SUMPRODUCT((Lançamentos!$C$5:$C$2000=$A8)*(Lançamentos!$E$5:$E$2000="Despesa")*(YEAR(Lançamentos!$A$5:$A$2000)=$B$3)*(MONTH(Lançamentos!$A$5:$A$2000)=2)*Lançamentos!$G$5:$G$2000) | G8: =E8-F8 | H8: 0 | I8: =SUMPRODUCT((Lançamentos!$C$5:$C$2000=$A8)*(Lançamentos!$E$5:$E$2000="Despesa")*(YEAR(Lançamentos!$A$5:$A$2000)=$B$3)*(MONTH(Lançamentos!$A$5:$A$2000)=3)*Lançamentos!$G$5:$G$2000) | J8: =H8-I8 | K8: 0 | L8: =SUMPRODUCT((Lançamentos!$C$5:$C$2000=$A8)*(Lançamentos!$E$5:$E$2000="Despesa")*(YEAR(Lançamentos!$A$5:$A$2000)=$B$3)*(MONTH(Lançamentos!$A$5:$A$2000)=4)*Lançamentos!$G$5:$G$2000) | M8: =K8-L8 | N8: 0 | O8: =SUMPRODUCT((Lançamentos!$C$5:$C$2000=$A8)*(Lançamentos!$E$5:$E$2000="Despesa")*(YEAR(Lançamentos!$A$5:$A$2000)=$B$3)*(MONTH(Lançamentos!$A$5:$A$2000)=5)*Lançamentos!$G$5:$G$2000) | P8: =N8-O8 | Q8: 0 | R8: =SUMPRODUCT((Lançamentos!$C$5:$C$2000=$A8)*(Lançamentos!$E$5:$E$2000="Despesa")*(YEAR(Lançamentos!$A$5:$A$2000)=$B$3)*(MONTH(Lançamentos!$A$5:$A$2000)=6)*Lançamentos!$G$5:$G$2000) | S8: =Q8-R8 | T8: 0 | U8: =SUMPRODUCT((Lançamentos!$C$5:$C$2000=$A8)*(Lançamentos!$E$5:$E$2000="Despesa")*(YEAR(Lançamentos!$A$5:$A$2000)=$B$3)*(MONTH(Lançamentos!$A$5:$A$2000)=7)*Lançamentos!$G$5:$G$2000) | V8: =T8-U8 | W8: 0 | X8: =SUMPRODUCT((Lançamentos!$C$5:$C$2000=$A8)*(Lançamentos!$E$5:$E$2000="Despesa")*(YEAR(Lançamentos!$A$5:$A$2000)=$B$3)*(MONTH(Lançamentos!$A$5:$A$2000)=8)*Lançamentos!$G$5:$G$2000) | Y8: =W8-X8 | Z8: 0 | AA8: =SUMPRODUCT((Lançamentos!$C$5:$C$2000=$A8)*(Lançamentos!$E$5:$E$2000="Despesa")*(YEAR(Lançamentos!$A$5:$A$2000)=$B$3)*(MONTH(Lançamentos!$A$5:$A$2000)=9)*Lançamentos!$G$5:$G$2000) | AB8: =Z8-AA8 | AC8: 0 | AD8: =SUMPRODUCT((Lançamentos!$C$5:$C$2000=$A8)*(Lançamentos!$E$5:$E$2000="Despesa")*(YEAR(Lançamentos!$A$5:$A$2000)=$B$3)*(MONTH(Lançamentos!$A$5:$A$2000)=10)*Lançamentos!$G$5:$G$2000) | AE8: =AC8-AD8 | AF8: 0 | AG8: =SUMPRODUCT((Lançamentos!$C$5:$C$2000=$A8)*(Lançamentos!$E$5:$E$2000="Despesa")*(YEAR(Lançamentos!$A$5:$A$2000)=$B$3)*(MONTH(Lançamentos!$A$5:$A$2000)=11)*Lançamentos!$G$5:$G$2000) | AH8: =AF8-AG8 | AI8: 0 | AJ8: =SUMPRODUCT((Lançamentos!$C$5:$C$2000=$A8)*(Lançamentos!$E$5:$E$2000="Despesa")*(YEAR(Lançamentos!$A$5:$A$2000)=$B$3)*(MONTH(Lançamentos!$A$5:$A$2000)=12)*Lançamentos!$G$5:$G$2000) | AK8: =AI8-AJ8
A9: Educação | B9: 0 | C9: =SUMPRODUCT((Lançamentos!$C$5:$C$2000=$A9)*(Lançamentos!$E$5:$E$2000="Despesa")*(YEAR(Lançamentos!$A$5:$A$2000)=$B$3)*(MONTH(Lançamentos!$A$5:$A$2000)=1)*Lançamentos!$G$5:$G$2000) | D9: =B9-C9 | E9: 0 | F9: =SUMPRODUCT((Lançamentos!$C$5:$C$2000=$A9)*(Lançamentos!$E$5:$E$2000="Despesa")*(YEAR(Lançamentos!$A$5:$A$2000)=$B$3)*(MONTH(Lançamentos!$A$5:$A$2000)=2)*Lançamentos!$G$5:$G$2000) | G9: =E9-F9 | H9: 0 | I9: =SUMPRODUCT((Lançamentos!$C$5:$C$2000=$A9)*(Lançamentos!$E$5:$E$2000="Despesa")*(YEAR(Lançamentos!$A$5:$A$2000)=$B$3)*(MONTH(Lançamentos!$A$5:$A$2000)=3)*Lançamentos!$G$5:$G$2000) | J9: =H9-I9 | K9: 0 | L9: =SUMPRODUCT((Lançamentos!$C$5:$C$2000=$A9)*(Lançamentos!$E$5:$E$2000="Despesa")*(YEAR(Lançamentos!$A$5:$A$2000)=$B$3)*(MONTH(Lançamentos!$A$5:$A$2000)=4)*Lançamentos!$G$5:$G$2000) | M9: =K9-L9 | N9: 0 | O9: =SUMPRODUCT((Lançamentos!$C$5:$C$2000=$A9)*(Lançamentos!$E$5:$E$2000="Despesa")*(YEAR(Lançamentos!$A$5:$A$2000)=$B$3)*(MONTH(Lançamentos!$A$5:$A$2000)=5)*Lançamentos!$G$5:$G$2000) | P9: =N9-O9 | Q9: 0 | R9: =SUMPRODUCT((Lançamentos!$C$5:$C$2000=$A9)*(Lançamentos!$E$5:$E$2000="Despesa")*(YEAR(Lançamentos!$A$5:$A$2000)=$B$3)*(MONTH(Lançamentos!$A$5:$A$2000)=6)*Lançamentos!$G$5:$G$2000) | S9: =Q9-R9 | T9: 0 | U9: =SUMPRODUCT((Lançamentos!$C$5:$C$2000=$A9)*(Lançamentos!$E$5:$E$2000="Despesa")*(YEAR(Lançamentos!$A$5:$A$2000)=$B$3)*(MONTH(Lançamentos!$A$5:$A$2000)=7)*Lançamentos!$G$5:$G$2000) | V9: =T9-U9 | W9: 0 | X9: =SUMPRODUCT((Lançamentos!$C$5:$C$2000=$A9)*(Lançamentos!$E$5:$E$2000="Despesa")*(YEAR(Lançamentos!$A$5:$A$2000)=$B$3)*(MONTH(Lançamentos!$A$5:$A$2000)=8)*Lançamentos!$G$5:$G$2000) | Y9: =W9-X9 | Z9: 0 | AA9: =SUMPRODUCT((Lançamentos!$C$5:$C$2000=$A9)*(Lançamentos!$E$5:$E$2000="Despesa")*(YEAR(Lançamentos!$A$5:$A$2000)=$B$3)*(MONTH(Lançamentos!$A$5:$A$2000)=9)*Lançamentos!$G$5:$G$2000) | AB9: =Z9-AA9 | AC9: 0 | AD9: =SUMPRODUCT((Lançamentos!$C$5:$C$2000=$A9)*(Lançamentos!$E$5:$E$2000="Despesa")*(YEAR(Lançamentos!$A$5:$A$2000)=$B$3)*(MONTH(Lançamentos!$A$5:$A$2000)=10)*Lançamentos!$G$5:$G$2000) | AE9: =AC9-AD9 | AF9: 0 | AG9: =SUMPRODUCT((Lançamentos!$C$5:$C$2000=$A9)*(Lançamentos!$E$5:$E$2000="Despesa")*(YEAR(Lançamentos!$A$5:$A$2000)=$B$3)*(MONTH(Lançamentos!$A$5:$A$2000)=11)*Lançamentos!$G$5:$G$2000) | AH9: =AF9-AG9 | AI9: 0 | AJ9: =SUMPRODUCT((Lançamentos!$C$5:$C$2000=$A9)*(Lançamentos!$E$5:$E$2000="Despesa")*(YEAR(Lançamentos!$A$5:$A$2000)=$B$3)*(MONTH(Lançamentos!$A$5:$A$2000)=12)*Lançamentos!$G$5:$G$2000) | AK9: =AI9-AJ9
A10: Investimentos | B10: 0 | C10: =SUMPRODUCT((Lançamentos!$C$5:$C$2000=$A10)*(Lançamentos!$E$5:$E$2000="Despesa")*(YEAR(Lançamentos!$A$5:$A$2000)=$B$3)*(MONTH(Lançamentos!$A$5:$A$2000)=1)*Lançamentos!$G$5:$G$2000) | D10: =B10-C10 | E10: 0 | F10: =SUMPRODUCT((Lançamentos!$C$5:$C$2000=$A10)*(Lançamentos!$E$5:$E$2000="Despesa")*(YEAR(Lançamentos!$A$5:$A$2000)=$B$3)*(MONTH(Lançamentos!$A$5:$A$2000)=2)*Lançamentos!$G$5:$G$2000) | G10: =E10-F10 | H10: 0 | I10: =SUMPRODUCT((Lançamentos!$C$5:$C$2000=$A10)*(Lançamentos!$E$5:$E$2000="Despesa")*(YEAR(Lançamentos!$A$5:$A$2000)=$B$3)*(MONTH(Lançamentos!$A$5:$A$2000)=3)*Lançamentos!$G$5:$G$2000) | J10: =H10-I10 | K10: 0 | L10: =SUMPRODUCT((Lançamentos!$C$5:$C$2000=$A10)*(Lançamentos!$E$5:$E$2000="Despesa")*(YEAR(Lançamentos!$A$5:$A$2000)=$B$3)*(MONTH(Lançamentos!$A$5:$A$2000)=4)*Lançamentos!$G$5:$G$2000) | M10: =K10-L10 | N10: 0 | O10: =SUMPRODUCT((Lançamentos!$C$5:$C$2000=$A10)*(Lançamentos!$E$5:$E$2000="Despesa")*(YEAR(Lançamentos!$A$5:$A$2000)=$B$3)*(MONTH(Lançamentos!$A$5:$A$2000)=5)*Lançamentos!$G$5:$G$2000) | P10: =N10-O10 | Q10: 0 | R10: =SUMPRODUCT((Lançamentos!$C$5:$C$2000=$A10)*(Lançamentos!$E$5:$E$2000="Despesa")*(YEAR(Lançamentos!$A$5:$A$2000)=$B$3)*(MONTH(Lançamentos!$A$5:$A$2000)=6)*Lançamentos!$G$5:$G$2000) | S10: =Q10-R10 | T10: 0 | U10: =SUMPRODUCT((Lançamentos!$C$5:$C$2000=$A10)*(Lançamentos!$E$5:$E$2000="Despesa")*(YEAR(Lançamentos!$A$5:$A$2000)=$B$3)*(MONTH(Lançamentos!$A$5:$A$2000)=7)*Lançamentos!$G$5:$G$2000) | V10: =T10-U10 | W10: 0 | X10: =SUMPRODUCT((Lançamentos!$C$5:$C$2000=$A10)*(Lançamentos!$E$5:$E$2000="Despesa")*(YEAR(Lançamentos!$A$5:$A$2000)=$B$3)*(MONTH(Lançamentos!$A$5:$A$2000)=8)*Lançamentos!$G$5:$G$2000) | Y10: =W10-X10 | Z10: 0 | AA10: =SUMPRODUCT((Lançamentos!$C$5:$C$2000=$A10)*(Lançamentos!$E$5:$E$2000="Despesa")*(YEAR(Lançamentos!$A$5:$A$2000)=$B$3)*(MONTH(Lançamentos!$A$5:$A$2000)=9)*Lançamentos!$G$5:$G$2000) | AB10: =Z10-AA10 | AC10: 0 | AD10: =SUMPRODUCT((Lançamentos!$C$5:$C$2000=$A10)*(Lançamentos!$E$5:$E$2000="Despesa")*(YEAR(Lançamentos!$A$5:$A$2000)=$B$3)*(MONTH(Lançamentos!$A$5:$A$2000)=10)*Lançamentos!$G$5:$G$2000) | AE10: =AC10-AD10 | AF10: 0 | AG10: =SUMPRODUCT((Lançamentos!$C$5:$C$2000=$A10)*(Lançamentos!$E$5:$E$2000="Despesa")*(YEAR(Lançamentos!$A$5:$A$2000)=$B$3)*(MONTH(Lançamentos!$A$5:$A$2000)=11)*Lançamentos!$G$5:$G$2000) | AH10: =AF10-AG10 | AI10: 0 | AJ10: =SUMPRODUCT((Lançamentos!$C$5:$C$2000=$A10)*(Lançamentos!$E$5:$E$2000="Despesa")*(YEAR(Lançamentos!$A$5:$A$2000)=$B$3)*(MONTH(Lançamentos!$A$5:$A$2000)=12)*Lançamentos!$G$5:$G$2000) | AK10: =AI10-AJ10
A11: Lazer | B11: 0 | C11: =SUMPRODUCT((Lançamentos!$C$5:$C$2000=$A11)*(Lançamentos!$E$5:$E$2000="Despesa")*(YEAR(Lançamentos!$A$5:$A$2000)=$B$3)*(MONTH(Lançamentos!$A$5:$A$2000)=1)*Lançamentos!$G$5:$G$2000) | D11: =B11-C11 | E11: 0 | F11: =SUMPRODUCT((Lançamentos!$C$5:$C$2000=$A11)*(Lançamentos!$E$5:$E$2000="Despesa")*(YEAR(Lançamentos!$A$5:$A$2000)=$B$3)*(MONTH(Lançamentos!$A$5:$A$2000)=2)*Lançamentos!$G$5:$G$2000) | G11: =E11-F11 | H11: 0 | I11: =SUMPRODUCT((Lançamentos!$C$5:$C$2000=$A11)*(Lançamentos!$E$5:$E$2000="Despesa")*(YEAR(Lançamentos!$A$5:$A$2000)=$B$3)*(MONTH(Lançamentos!$A$5:$A$2000)=3)*Lançamentos!$G$5:$G$2000) | J11: =H11-I11 | K11: 0 | L11: =SUMPRODUCT((Lançamentos!$C$5:$C$2000=$A11)*(Lançamentos!$E$5:$E$2000="Despesa")*(YEAR(Lançamentos!$A$5:$A$2000)=$B$3)*(MONTH(Lançamentos!$A$5:$A$2000)=4)*Lançamentos!$G$5:$G$2000) | M11: =K11-L11 | N11: 0 | O11: =SUMPRODUCT((Lançamentos!$C$5:$C$2000=$A11)*(Lançamentos!$E$5:$E$2000="Despesa")*(YEAR(Lançamentos!$A$5:$A$2000)=$B$3)*(MONTH(Lançamentos!$A$5:$A$2000)=5)*Lançamentos!$G$5:$G$2000) | P11: =N11-O11 | Q11: 0 | R11: =SUMPRODUCT((Lançamentos!$C$5:$C$2000=$A11)*(Lançamentos!$E$5:$E$2000="Despesa")*(YEAR(Lançamentos!$A$5:$A$2000)=$B$3)*(MONTH(Lançamentos!$A$5:$A$2000)=6)*Lançamentos!$G$5:$G$2000) | S11: =Q11-R11 | T11: 0 | U11: =SUMPRODUCT((Lançamentos!$C$5:$C$2000=$A11)*(Lançamentos!$E$5:$E$2000="Despesa")*(YEAR(Lançamentos!$A$5:$A$2000)=$B$3)*(MONTH(Lançamentos!$A$5:$A$2000)=7)*Lançamentos!$G$5:$G$2000) | V11: =T11-U11 | W11: 0 | X11: =SUMPRODUCT((Lançamentos!$C$5:$C$2000=$A11)*(Lançamentos!$E$5:$E$2000="Despesa")*(YEAR(Lançamentos!$A$5:$A$2000)=$B$3)*(MONTH(Lançamentos!$A$5:$A$2000)=8)*Lançamentos!$G$5:$G$2000) | Y11: =W11-X11 | Z11: 0 | AA11: =SUMPRODUCT((Lançamentos!$C$5:$C$2000=$A11)*(Lançamentos!$E$5:$E$2000="Despesa")*(YEAR(Lançamentos!$A$5:$A$2000)=$B$3)*(MONTH(Lançamentos!$A$5:$A$2000)=9)*Lançamentos!$G$5:$G$2000) | AB11: =Z11-AA11 | AC11: 0 | AD11: =SUMPRODUCT((Lançamentos!$C$5:$C$2000=$A11)*(Lançamentos!$E$5:$E$2000="Despesa")*(YEAR(Lançamentos!$A$5:$A$2000)=$B$3)*(MONTH(Lançamentos!$A$5:$A$2000)=10)*Lançamentos!$G$5:$G$2000) | AE11: =AC11-AD11 | AF11: 0 | AG11: =SUMPRODUCT((Lançamentos!$C$5:$C$2000=$A11)*(Lançamentos!$E$5:$E$2000="Despesa")*(YEAR(Lançamentos!$A$5:$A$2000)=$B$3)*(MONTH(Lançamentos!$A$5:$A$2000)=11)*Lançamentos!$G$5:$G$2000) | AH11: =AF11-AG11 | AI11: 0 | AJ11: =SUMPRODUCT((Lançamentos!$C$5:$C$2000=$A11)*(Lançamentos!$E$5:$E$2000="Despesa")*(YEAR(Lançamentos!$A$5:$A$2000)=$B$3)*(MONTH(Lançamentos!$A$5:$A$2000)=12)*Lançamentos!$G$5:$G$2000) | AK11: =AI11-AJ11
A12: Moradia | B12: 0 | C12: =SUMPRODUCT((Lançamentos!$C$5:$C$2000=$A12)*(Lançamentos!$E$5:$E$2000="Despesa")*(YEAR(Lançamentos!$A$5:$A$2000)=$B$3)*(MONTH(Lançamentos!$A$5:$A$2000)=1)*Lançamentos!$G$5:$G$2000) | D12: =B12-C12 | E12: 0 | F12: =SUMPRODUCT((Lançamentos!$C$5:$C$2000=$A12)*(Lançamentos!$E$5:$E$2000="Despesa")*(YEAR(Lançamentos!$A$5:$A$2000)=$B$3)*(MONTH(Lançamentos!$A$5:$A$2000)=2)*Lançamentos!$G$5:$G$2000) | G12: =E12-F12 | H12: 0 | I12: =SUMPRODUCT((Lançamentos!$C$5:$C$2000=$A12)*(Lançamentos!$E$5:$E$2000="Despesa")*(YEAR(Lançamentos!$A$5:$A$2000)=$B$3)*(MONTH(Lançamentos!$A$5:$A$2000)=3)*Lançamentos!$G$5:$G$2000) | J12: =H12-I12 | K12: 0 | L12: =SUMPRODUCT((Lançamentos!$C$5:$C$2000=$A12)*(Lançamentos!$E$5:$E$2000="Despesa")*(YEAR(Lançamentos!$A$5:$A$2000)=$B$3)*(MONTH(Lançamentos!$A$5:$A$2000)=4)*Lançamentos!$G$5:$G$2000) | M12: =K12-L12 | N12: 0 | O12: =SUMPRODUCT((Lançamentos!$C$5:$C$2000=$A12)*(Lançamentos!$E$5:$E$2000="Despesa")*(YEAR(Lançamentos!$A$5:$A$2000)=$B$3)*(MONTH(Lançamentos!$A$5:$A$2000)=5)*Lançamentos!$G$5:$G$2000) | P12: =N12-O12 | Q12: 0 | R12: =SUMPRODUCT((Lançamentos!$C$5:$C$2000=$A12)*(Lançamentos!$E$5:$E$2000="Despesa")*(YEAR(Lançamentos!$A$5:$A$2000)=$B$3)*(MONTH(Lançamentos!$A$5:$A$2000)=6)*Lançamentos!$G$5:$G$2000) | S12: =Q12-R12 | T12: 0 | U12: =SUMPRODUCT((Lançamentos!$C$5:$C$2000=$A12)*(Lançamentos!$E$5:$E$2000="Despesa")*(YEAR(Lançamentos!$A$5:$A$2000)=$B$3)*(MONTH(Lançamentos!$A$5:$A$2000)=7)*Lançamentos!$G$5:$G$2000) | V12: =T12-U12 | W12: 0 | X12: =SUMPRODUCT((Lançamentos!$C$5:$C$2000=$A12)*(Lançamentos!$E$5:$E$2000="Despesa")*(YEAR(Lançamentos!$A$5:$A$2000)=$B$3)*(MONTH(Lançamentos!$A$5:$A$2000)=8)*Lançamentos!$G$5:$G$2000) | Y12: =W12-X12 | Z12: 0 | AA12: =SUMPRODUCT((Lançamentos!$C$5:$C$2000=$A12)*(Lançamentos!$E$5:$E$2000="Despesa")*(YEAR(Lançamentos!$A$5:$A$2000)=$B$3)*(MONTH(Lançamentos!$A$5:$A$2000)=9)*Lançamentos!$G$5:$G$2000) | AB12: =Z12-AA12 | AC12: 0 | AD12: =SUMPRODUCT((Lançamentos!$C$5:$C$2000=$A12)*(Lançamentos!$E$5:$E$2000="Despesa")*(YEAR(Lançamentos!$A$5:$A$2000)=$B$3)*(MONTH(Lançamentos!$A$5:$A$2000)=10)*Lançamentos!$G$5:$G$2000) | AE12: =AC12-AD12 | AF12: 0 | AG12: =SUMPRODUCT((Lançamentos!$C$5:$C$2000=$A12)*(Lançamentos!$E$5:$E$2000="Despesa")*(YEAR(Lançamentos!$A$5:$A$2000)=$B$3)*(MONTH(Lançamentos!$A$5:$A$2000)=11)*Lançamentos!$G$5:$G$2000) | AH12: =AF12-AG12 | AI12: 0 | AJ12: =SUMPRODUCT((Lançamentos!$C$5:$C$2000=$A12)*(Lançamentos!$E$5:$E$2000="Despesa")*(YEAR(Lançamentos!$A$5:$A$2000)=$B$3)*(MONTH(Lançamentos!$A$5:$A$2000)=12)*Lançamentos!$G$5:$G$2000) | AK12: =AI12-AJ12
A13: Outros | B13: 0 | C13: =SUMPRODUCT((Lançamentos!$C$5:$C$2000=$A13)*(Lançamentos!$E$5:$E$2000="Despesa")*(YEAR(Lançamentos!$A$5:$A$2000)=$B$3)*(MONTH(Lançamentos!$A$5:$A$2000)=1)*Lançamentos!$G$5:$G$2000) | D13: =B13-C13 | E13: 0 | F13: =SUMPRODUCT((Lançamentos!$C$5:$C$2000=$A13)*(Lançamentos!$E$5:$E$2000="Despesa")*(YEAR(Lançamentos!$A$5:$A$2000)=$B$3)*(MONTH(Lançamentos!$A$5:$A$2000)=2)*Lançamentos!$G$5:$G$2000) | G13: =E13-F13 | H13: 0 | I13: =SUMPRODUCT((Lançamentos!$C$5:$C$2000=$A13)*(Lançamentos!$E$5:$E$2000="Despesa")*(YEAR(Lançamentos!$A$5:$A$2000)=$B$3)*(MONTH(Lançamentos!$A$5:$A$2000)=3)*Lançamentos!$G$5:$G$2000) | J13: =H13-I13 | K13: 0 | L13: =SUMPRODUCT((Lançamentos!$C$5:$C$2000=$A13)*(Lançamentos!$E$5:$E$2000="Despesa")*(YEAR(Lançamentos!$A$5:$A$2000)=$B$3)*(MONTH(Lançamentos!$A$5:$A$2000)=4)*Lançamentos!$G$5:$G$2000) | M13: =K13-L13 | N13: 0 | O13: =SUMPRODUCT((Lançamentos!$C$5:$C$2000=$A13)*(Lançamentos!$E$5:$E$2000="Despesa")*(YEAR(Lançamentos!$A$5:$A$2000)=$B$3)*(MONTH(Lançamentos!$A$5:$A$2000)=5)*Lançamentos!$G$5:$G$2000) | P13: =N13-O13 | Q13: 0 | R13: =SUMPRODUCT((Lançamentos!$C$5:$C$2000=$A13)*(Lançamentos!$E$5:$E$2000="Despesa")*(YEAR(Lançamentos!$A$5:$A$2000)=$B$3)*(MONTH(Lançamentos!$A$5:$A$2000)=6)*Lançamentos!$G$5:$G$2000) | S13: =Q13-R13 | T13: 0 | U13: =SUMPRODUCT((Lançamentos!$C$5:$C$2000=$A13)*(Lançamentos!$E$5:$E$2000="Despesa")*(YEAR(Lançamentos!$A$5:$A$2000)=$B$3)*(MONTH(Lançamentos!$A$5:$A$2000)=7)*Lançamentos!$G$5:$G$2000) | V13: =T13-U13 | W13: 0 | X13: =SUMPRODUCT((Lançamentos!$C$5:$C$2000=$A13)*(Lançamentos!$E$5:$E$2000="Despesa")*(YEAR(Lançamentos!$A$5:$A$2000)=$B$3)*(MONTH(Lançamentos!$A$5:$A$2000)=8)*Lançamentos!$G$5:$G$2000) | Y13: =W13-X13 | Z13: 0 | AA13: =SUMPRODUCT((Lançamentos!$C$5:$C$2000=$A13)*(Lançamentos!$E$5:$E$2000="Despesa")*(YEAR(Lançamentos!$A$5:$A$2000)=$B$3)*(MONTH(Lançamentos!$A$5:$A$2000)=9)*Lançamentos!$G$5:$G$2000) | AB13: =Z13-AA13 | AC13: 0 | AD13: =SUMPRODUCT((Lançamentos!$C$5:$C$2000=$A13)*(Lançamentos!$E$5:$E$2000="Despesa")*(YEAR(Lançamentos!$A$5:$A$2000)=$B$3)*(MONTH(Lançamentos!$A$5:$A$2000)=10)*Lançamentos!$G$5:$G$2000) | AE13: =AC13-AD13 | AF13: 0 | AG13: =SUMPRODUCT((Lançamentos!$C$5:$C$2000=$A13)*(Lançamentos!$E$5:$E$2000="Despesa")*(YEAR(Lançamentos!$A$5:$A$2000)=$B$3)*(MONTH(Lançamentos!$A$5:$A$2000)=11)*Lançamentos!$G$5:$G$2000) | AH13: =AF13-AG13 | AI13: 0 | AJ13: =SUMPRODUCT((Lançamentos!$C$5:$C$2000=$A13)*(Lançamentos!$E$5:$E$2000="Despesa")*(YEAR(Lançamentos!$A$5:$A$2000)=$B$3)*(MONTH(Lançamentos!$A$5:$A$2000)=12)*Lançamentos!$G$5:$G$2000) | AK13: =AI13-AJ13
A14: Saúde | B14: 0 | C14: =SUMPRODUCT((Lançamentos!$C$5:$C$2000=$A14)*(Lançamentos!$E$5:$E$2000="Despesa")*(YEAR(Lançamentos!$A$5:$A$2000)=$B$3)*(MONTH(Lançamentos!$A$5:$A$2000)=1)*Lançamentos!$G$5:$G$2000) | D14: =B14-C14 | E14: 0 | F14: =SUMPRODUCT((Lançamentos!$C$5:$C$2000=$A14)*(Lançamentos!$E$5:$E$2000="Despesa")*(YEAR(Lançamentos!$A$5:$A$2000)=$B$3)*(MONTH(Lançamentos!$A$5:$A$2000)=2)*Lançamentos!$G$5:$G$2000) | G14: =E14-F14 | H14: 0 | I14: =SUMPRODUCT((Lançamentos!$C$5:$C$2000=$A14)*(Lançamentos!$E$5:$E$2000="Despesa")*(YEAR(Lançamentos!$A$5:$A$2000)=$B$3)*(MONTH(Lançamentos!$A$5:$A$2000)=3)*Lançamentos!$G$5:$G$2000) | J14: =H14-I14 | K14: 0 | L14: =SUMPRODUCT((Lançamentos!$C$5:$C$2000=$A14)*(Lançamentos!$E$5:$E$2000="Despesa")*(YEAR(Lançamentos!$A$5:$A$2000)=$B$3)*(MONTH(Lançamentos!$A$5:$A$2000)=4)*Lançamentos!$G$5:$G$2000) | M14: =K14-L14 | N14: 0 | O14: =SUMPRODUCT((Lançamentos!$C$5:$C$2000=$A14)*(Lançamentos!$E$5:$E$2000="Despesa")*(YEAR(Lançamentos!$A$5:$A$2000)=$B$3)*(MONTH(Lançamentos!$A$5:$A$2000)=5)*Lançamentos!$G$5:$G$2000) | P14: =N14-O14 | Q14: 0 | R14: =SUMPRODUCT((Lançamentos!$C$5:$C$2000=$A14)*(Lançamentos!$E$5:$E$2000="Despesa")*(YEAR(Lançamentos!$A$5:$A$2000)=$B$3)*(MONTH(Lançamentos!$A$5:$A$2000)=6)*Lançamentos!$G$5:$G$2000) | S14: =Q14-R14 | T14: 0 | U14: =SUMPRODUCT((Lançamentos!$C$5:$C$2000=$A14)*(Lançamentos!$E$5:$E$2000="Despesa")*(YEAR(Lançamentos!$A$5:$A$2000)=$B$3)*(MONTH(Lançamentos!$A$5:$A$2000)=7)*Lançamentos!$G$5:$G$2000) | V14: =T14-U14 | W14: 0 | X14: =SUMPRODUCT((Lançamentos!$C$5:$C$2000=$A14)*(Lançamentos!$E$5:$E$2000="Despesa")*(YEAR(Lançamentos!$A$5:$A$2000)=$B$3)*(MONTH(Lançamentos!$A$5:$A$2000)=8)*Lançamentos!$G$5:$G$2000) | Y14: =W14-X14 | Z14: 0 | AA14: =SUMPRODUCT((Lançamentos!$C$5:$C$2000=$A14)*(Lançamentos!$E$5:$E$2000="Despesa")*(YEAR(Lançamentos!$A$5:$A$2000)=$B$3)*(MONTH(Lançamentos!$A$5:$A$2000)=9)*Lançamentos!$G$5:$G$2000) | AB14: =Z14-AA14 | AC14: 0 | AD14: =SUMPRODUCT((Lançamentos!$C$5:$C$2000=$A14)*(Lançamentos!$E$5:$E$2000="Despesa")*(YEAR(Lançamentos!$A$5:$A$2000)=$B$3)*(MONTH(Lançamentos!$A$5:$A$2000)=10)*Lançamentos!$G$5:$G$2000) | AE14: =AC14-AD14 | AF14: 0 | AG14: =SUMPRODUCT((Lançamentos!$C$5:$C$2000=$A14)*(Lançamentos!$E$5:$E$2000="Despesa")*(YEAR(Lançamentos!$A$5:$A$2000)=$B$3)*(MONTH(Lançamentos!$A$5:$A$2000)=11)*Lançamentos!$G$5:$G$2000) | AH14: =AF14-AG14 | AI14: 0 | AJ14: =SUMPRODUCT((Lançamentos!$C$5:$C$2000=$A14)*(Lançamentos!$E$5:$E$2000="Despesa")*(YEAR(Lançamentos!$A$5:$A$2000)=$B$3)*(MONTH(Lançamentos!$A$5:$A$2000)=12)*Lançamentos!$G$5:$G$2000) | AK14: =AI14-AJ14
A15: Transporte | B15: 0 | C15: =SUMPRODUCT((Lançamentos!$C$5:$C$2000=$A15)*(Lançamentos!$E$5:$E$2000="Despesa")*(YEAR(Lançamentos!$A$5:$A$2000)=$B$3)*(MONTH(Lançamentos!$A$5:$A$2000)=1)*Lançamentos!$G$5:$G$2000) | D15: =B15-C15 | E15: 0 | F15: =SUMPRODUCT((Lançamentos!$C$5:$C$2000=$A15)*(Lançamentos!$E$5:$E$2000="Despesa")*(YEAR(Lançamentos!$A$5:$A$2000)=$B$3)*(MONTH(Lançamentos!$A$5:$A$2000)=2)*Lançamentos!$G$5:$G$2000) | G15: =E15-F15 | H15: 0 | I15: =SUMPRODUCT((Lançamentos!$C$5:$C$2000=$A15)*(Lançamentos!$E$5:$E$2000="Despesa")*(YEAR(Lançamentos!$A$5:$A$2000)=$B$3)*(MONTH(Lançamentos!$A$5:$A$2000)=3)*Lançamentos!$G$5:$G$2000) | J15: =H15-I15 | K15: 0 | L15: =SUMPRODUCT((Lançamentos!$C$5:$C$2000=$A15)*(Lançamentos!$E$5:$E$2000="Despesa")*(YEAR(Lançamentos!$A$5:$A$2000)=$B$3)*(MONTH(Lançamentos!$A$5:$A$2000)=4)*Lançamentos!$G$5:$G$2000) | M15: =K15-L15 | N15: 0 | O15: =SUMPRODUCT((Lançamentos!$C$5:$C$2000=$A15)*(Lançamentos!$E$5:$E$2000="Despesa")*(YEAR(Lançamentos!$A$5:$A$2000)=$B$3)*(MONTH(Lançamentos!$A$5:$A$2000)=5)*Lançamentos!$G$5:$G$2000) | P15: =N15-O15 | Q15: 0 | R15: =SUMPRODUCT((Lançamentos!$C$5:$C$2000=$A15)*(Lançamentos!$E$5:$E$2000="Despesa")*(YEAR(Lançamentos!$A$5:$A$2000)=$B$3)*(MONTH(Lançamentos!$A$5:$A$2000)=6)*Lançamentos!$G$5:$G$2000) | S15: =Q15-R15 | T15: 0 | U15: =SUMPRODUCT((Lançamentos!$C$5:$C$2000=$A15)*(Lançamentos!$E$5:$E$2000="Despesa")*(YEAR(Lançamentos!$A$5:$A$2000)=$B$3)*(MONTH(Lançamentos!$A$5:$A$2000)=7)*Lançamentos!$G$5:$G$2000) | V15: =T15-U15 | W15: 0 | X15: =SUMPRODUCT((Lançamentos!$C$5:$C$2000=$A15)*(Lançamentos!$E$5:$E$2000="Despesa")*(YEAR(Lançamentos!$A$5:$A$2000)=$B$3)*(MONTH(Lançamentos!$A$5:$A$2000)=8)*Lançamentos!$G$5:$G$2000) | Y15: =W15-X15 | Z15: 0 | AA15: =SUMPRODUCT((Lançamentos!$C$5:$C$2000=$A15)*(Lançamentos!$E$5:$E$2000="Despesa")*(YEAR(Lançamentos!$A$5:$A$2000)=$B$3)*(MONTH(Lançamentos!$A$5:$A$2000)=9)*Lançamentos!$G$5:$G$2000) | AB15: =Z15-AA15 | AC15: 0 | AD15: =SUMPRODUCT((Lançamentos!$C$5:$C$2000=$A15)*(Lançamentos!$E$5:$E$2000="Despesa")*(YEAR(Lançamentos!$A$5:$A$2000)=$B$3)*(MONTH(Lançamentos!$A$5:$A$2000)=10)*Lançamentos!$G$5:$G$2000) | AE15: =AC15-AD15 | AF15: 0 | AG15: =SUMPRODUCT((Lançamentos!$C$5:$C$2000=$A15)*(Lançamentos!$E$5:$E$2000="Despesa")*(YEAR(Lançamentos!$A$5:$A$2000)=$B$3)*(MONTH(Lançamentos!$A$5:$A$2000)=11)*Lançamentos!$G$5:$G$2000) | AH15: =AF15-AG15 | AI15: 0 | AJ15: =SUMPRODUCT((Lançamentos!$C$5:$C$2000=$A15)*(Lançamentos!$E$5:$E$2000="Despesa")*(YEAR(Lançamentos!$A$5:$A$2000)=$B$3)*(MONTH(Lançamentos!$A$5:$A$2000)=12)*Lançamentos!$G$5:$G$2000) | AK15: =AI15-AJ15
A16: Vestuário | B16: 0 | C16: =SUMPRODUCT((Lançamentos!$C$5:$C$2000=$A16)*(Lançamentos!$E$5:$E$2000="Despesa")*(YEAR(Lançamentos!$A$5:$A$2000)=$B$3)*(MONTH(Lançamentos!$A$5:$A$2000)=1)*Lançamentos!$G$5:$G$2000) | D16: =B16-C16 | E16: 0 | F16: =SUMPRODUCT((Lançamentos!$C$5:$C$2000=$A16)*(Lançamentos!$E$5:$E$2000="Despesa")*(YEAR(Lançamentos!$A$5:$A$2000)=$B$3)*(MONTH(Lançamentos!$A$5:$A$2000)=2)*Lançamentos!$G$5:$G$2000) | G16: =E16-F16 | H16: 0 | I16: =SUMPRODUCT((Lançamentos!$C$5:$C$2000=$A16)*(Lançamentos!$E$5:$E$2000="Despesa")*(YEAR(Lançamentos!$A$5:$A$2000)=$B$3)*(MONTH(Lançamentos!$A$5:$A$2000)=3)*Lançamentos!$G$5:$G$2000) | J16: =H16-I16 | K16: 0 | L16: =SUMPRODUCT((Lançamentos!$C$5:$C$2000=$A16)*(Lançamentos!$E$5:$E$2000="Despesa")*(YEAR(Lançamentos!$A$5:$A$2000)=$B$3)*(MONTH(Lançamentos!$A$5:$A$2000)=4)*Lançamentos!$G$5:$G$2000) | M16: =K16-L16 | N16: 0 | O16: =SUMPRODUCT((Lançamentos!$C$5:$C$2000=$A16)*(Lançamentos!$E$5:$E$2000="Despesa")*(YEAR(Lançamentos!$A$5:$A$2000)=$B$3)*(MONTH(Lançamentos!$A$5:$A$2000)=5)*Lançamentos!$G$5:$G$2000) | P16: =N16-O16 | Q16: 0 | R16: =SUMPRODUCT((Lançamentos!$C$5:$C$2000=$A16)*(Lançamentos!$E$5:$E$2000="Despesa")*(YEAR(Lançamentos!$A$5:$A$2000)=$B$3)*(MONTH(Lançamentos!$A$5:$A$2000)=6)*Lançamentos!$G$5:$G$2000) | S16: =Q16-R16 | T16: 0 | U16: =SUMPRODUCT((Lançamentos!$C$5:$C$2000=$A16)*(Lançamentos!$E$5:$E$2000="Despesa")*(YEAR(Lançamentos!$A$5:$A$2000)=$B$3)*(MONTH(Lançamentos!$A$5:$A$2000)=7)*Lançamentos!$G$5:$G$2000) | V16: =T16-U16 | W16: 0 | X16: =SUMPRODUCT((Lançamentos!$C$5:$C$2000=$A16)*(Lançamentos!$E$5:$E$2000="Despesa")*(YEAR(Lançamentos!$A$5:$A$2000)=$B$3)*(MONTH(Lançamentos!$A$5:$A$2000)=8)*Lançamentos!$G$5:$G$2000) | Y16: =W16-X16 | Z16: 0 | AA16: =SUMPRODUCT((Lançamentos!$C$5:$C$2000=$A16)*(Lançamentos!$E$5:$E$2000="Despesa")*(YEAR(Lançamentos!$A$5:$A$2000)=$B$3)*(MONTH(Lançamentos!$A$5:$A$2000)=9)*Lançamentos!$G$5:$G$2000) | AB16: =Z16-AA16 | AC16: 0 | AD16: =SUMPRODUCT((Lançamentos!$C$5:$C$2000=$A16)*(Lançamentos!$E$5:$E$2000="Despesa")*(YEAR(Lançamentos!$A$5:$A$2000)=$B$3)*(MONTH(Lançamentos!$A$5:$A$2000)=10)*Lançamentos!$G$5:$G$2000) | AE16: =AC16-AD16 | AF16: 0 | AG16: =SUMPRODUCT((Lançamentos!$C$5:$C$2000=$A16)*(Lançamentos!$E$5:$E$2000="Despesa")*(YEAR(Lançamentos!$A$5:$A$2000)=$B$3)*(MONTH(Lançamentos!$A$5:$A$2000)=11)*Lançamentos!$G$5:$G$2000) | AH16: =AF16-AG16 | AI16: 0 | AJ16: =SUMPRODUCT((Lançamentos!$C$5:$C$2000=$A16)*(Lançamentos!$E$5:$E$2000="Despesa")*(YEAR(Lançamentos!$A$5:$A$2000)=$B$3)*(MONTH(Lançamentos!$A$5:$A$2000)=12)*Lançamentos!$G$5:$G$2000) | AK16: =AI16-AJ16
A17: Total | B17: =SUM(B6:B16) | C17: =SUM(C6:C16) | D17: =B17-C17 | E17: =SUM(E6:E16) | F17: =SUM(F6:F16) | G17: =E17-F17 | H17: =SUM(H6:H16) | I17: =SUM(I6:I16) | J17: =H17-I17 | K17: =SUM(K6:K16) | L17: =SUM(L6:L16) | M17: =K17-L17 | N17: =SUM(N6:N16) | O17: =SUM(O6:O16) | P17: =N17-O17 | Q17: =SUM(Q6:Q16) | R17: =SUM(R6:R16) | S17: =Q17-R17 | T17: =SUM(T6:T16) | U17: =SUM(U6:U16) | V17: =T17-U17 | W17: =SUM(W6:W16) | X17: =SUM(X6:X16) | Y17: =W17-X17 | Z17: =SUM(Z6:Z16) | AA17: =SUM(AA6:AA16) | AB17: =Z17-AA17 | AC17: =SUM(AC6:AC16) | AD17: =SUM(AD6:AD16) | AE17: =AC17-AD17 | AF17: =SUM(AF6:AF16) | AG17: =SUM(AG6:AG16) | AH17: =AF17-AG17 | AI17: =SUM(AI6:AI16) | AJ17: =SUM(AJ6:AJ16) | AK17: =AI17-AJ17

Sheet Resumo
A1: Resumo Financeiro
A2: Visão consolidada a partir da aba Lançamentos. Ajuste o mês/ano de referência abaixo.
A4: Mês de Referência (1-12): | B4: 8
A5: Ano de Referência: | B5: 2026
A7: Total Receitas (mês) | B7: =SUMPRODUCT((Lançamentos!$E$5:$E$2000="Receita")*(YEAR(Lançamentos!$A$5:$A$2000)=$B$5)*(MONTH(Lançamentos!$A$5:$A$2000)=$B$4)*Lançamentos!$G$5:$G$2000)
A8: Total Despesas (mês) | B8: =SUMPRODUCT((Lançamentos!$E$5:$E$2000="Despesa")*(YEAR(Lançamentos!$A$5:$A$2000)=$B$5)*(MONTH(Lançamentos!$A$5:$A$2000)=$B$4)*Lançamentos!$G$5:$G$2000)
A9: Saldo do Mês | B9: =B7-B8
A10: Total Geral Receitas (todos os meses) | B10: =SUMIF(Lançamentos!$E$5:$E$2000,"Receita",Lançamentos!$G$5:$G$2000)
A11: Total Geral Despesas (todos os meses) | B11: =SUMIF(Lançamentos!$E$5:$E$2000,"Despesa",Lançamentos!$G$5:$G$2000)
A12: Saldo Geral | B12: =B10-B11
A14: Gasto por Categoria (mês de referência)
A15: Categoria | B15: Total Gasto
A16: Alimentação | B16: =SUMPRODUCT((Lançamentos!$C$5:$C$2000="Alimentação")*(YEAR(Lançamentos!$A$5:$A$2000)=$B$5)*(MONTH(Lançamentos!$A$5:$A$2000)=$B$4)*Lançamentos!$G$5:$G$2000)
A17: Cartão de Crédito | B17: =SUMPRODUCT((Lançamentos!$C$5:$C$2000="Cartão de Crédito")*(YEAR(Lançamentos!$A$5:$A$2000)=$B$5)*(MONTH(Lançamentos!$A$5:$A$2000)=$B$4)*Lançamentos!$G$5:$G$2000)
A18: Dívidas | B18: =SUMPRODUCT((Lançamentos!$C$5:$C$2000="Dívidas")*(YEAR(Lançamentos!$A$5:$A$2000)=$B$5)*(MONTH(Lançamentos!$A$5:$A$2000)=$B$4)*Lançamentos!$G$5:$G$2000)
A19: Educação | B19: =SUMPRODUCT((Lançamentos!$C$5:$C$2000="Educação")*(YEAR(Lançamentos!$A$5:$A$2000)=$B$5)*(MONTH(Lançamentos!$A$5:$A$2000)=$B$4)*Lançamentos!$G$5:$G$2000)
A20: Investimentos | B20: =SUMPRODUCT((Lançamentos!$C$5:$C$2000="Investimentos")*(YEAR(Lançamentos!$A$5:$A$2000)=$B$5)*(MONTH(Lançamentos!$A$5:$A$2000)=$B$4)*Lançamentos!$G$5:$G$2000)
A21: Lazer | B21: =SUMPRODUCT((Lançamentos!$C$5:$C$2000="Lazer")*(YEAR(Lançamentos!$A$5:$A$2000)=$B$5)*(MONTH(Lançamentos!$A$5:$A$2000)=$B$4)*Lançamentos!$G$5:$G$2000)
A22: Moradia | B22: =SUMPRODUCT((Lançamentos!$C$5:$C$2000="Moradia")*(YEAR(Lançamentos!$A$5:$A$2000)=$B$5)*(MONTH(Lançamentos!$A$5:$A$2000)=$B$4)*Lançamentos!$G$5:$G$2000)
A23: Outros | B23: =SUMPRODUCT((Lançamentos!$C$5:$C$2000="Outros")*(YEAR(Lançamentos!$A$5:$A$2000)=$B$5)*(MONTH(Lançamentos!$A$5:$A$2000)=$B$4)*Lançamentos!$G$5:$G$2000)
A24: Saúde | B24: =SUMPRODUCT((Lançamentos!$C$5:$C$2000="Saúde")*(YEAR(Lançamentos!$A$5:$A$2000)=$B$5)*(MONTH(Lançamentos!$A$5:$A$2000)=$B$4)*Lançamentos!$G$5:$G$2000)
A25: Transporte | B25: =SUMPRODUCT((Lançamentos!$C$5:$C$2000="Transporte")*(YEAR(Lançamentos!$A$5:$A$2000)=$B$5)*(MONTH(Lançamentos!$A$5:$A$2000)=$B$4)*Lançamentos!$G$5:$G$2000)
A26: Vestuário | B26: =SUMPRODUCT((Lançamentos!$C$5:$C$2000="Vestuário")*(YEAR(Lançamentos!$A$5:$A$2000)=$B$5)*(MONTH(Lançamentos!$A$5:$A$2000)=$B$4)*Lançamentos!$G$5:$G$2000)
