Workbook

Sheet Ficha_Funcionario
B2: Ficha do Funcionario
B3: Selecione o Codigo do funcionario na celula abaixo (dropdown) para ver todos os dados vinculados.
B5: Codigo: | C5: 263
B7: Nome | C7: =IFERROR(INDEX(Funcionarios!$B$3:$B$38,MATCH($C$5,Funcionarios!$A$3:$A$38,0)),"") -> JOAO CAVALCANTE CASTRO FILHO
B8: Cargo | C8: =IFERROR(INDEX(Funcionarios!$C$3:$C$38,MATCH($C$5,Funcionarios!$A$3:$A$38,0)),"") -> Assistente Administrativo
B9: Admissao | C9: =IFERROR(INDEX(Funcionarios!$D$3:$D$38,MATCH($C$5,Funcionarios!$A$3:$A$38,0)),"") -> 2015-05-11
B10: Salario | C10: =IFERROR(INDEX(Funcionarios!$E$3:$E$38,MATCH($C$5,Funcionarios!$A$3:$A$38,0)),"") -> 2470
B11: Departamento | C11: =IFERROR(INDEX(Funcionarios!$G$3:$G$38,MATCH($C$5,Funcionarios!$A$3:$A$38,0)),"") -> Administracao - Fabrica
B12: C. de Custo | C12: =IFERROR(INDEX(Funcionarios!$H$3:$H$38,MATCH($C$5,Funcionarios!$A$3:$A$38,0)),"") -> Fabrica ACME
B13: Nascimento | C13: =IFERROR(INDEX(Funcionarios!$I$3:$I$38,MATCH($C$5,Funcionarios!$A$3:$A$38,0)),"") -> 1966-05-04
B14: Sexo | C14: =IFERROR(INDEX(Funcionarios!$J$3:$J$38,MATCH($C$5,Funcionarios!$A$3:$A$38,0)),"") -> Masculino
B16: Total Liquido Recebido (todas as folhas) | C16: =SUMIF(Liquidos!$C:$C,$C$5,Liquidos!$E:$E) -> 2918.18
B17: Total Horas Extras (valor) | C17: =SUMIF(Horas_Extras!$C:$C,$C$5,Horas_Extras!$H:$H) -> 155.61
B18: Faltas (h) | C18: =IFERROR(INDEX(Faltas!$D$3:$D$38,MATCH(INDEX(Funcionarios!$B$3:$B$38,MATCH($C$5,Funcionarios!$A$3:$A$38,0)),Faltas!$A$3:$A$38,0)),"") -> 5.03
B19: Atestados (h) | C19: =IFERROR(INDEX(Atestados!$D$3:$D$38,MATCH(INDEX(Funcionarios!$B$3:$B$38,MATCH($C$5,Funcionarios!$A$3:$A$38,0)),Atestados!$A$3:$A$38,0)),"") -> 0
B20: Rescisao (se houver) - Liquido | C20: =IFERROR(INDEX(Rescisoes!$J$3:$J$8,MATCH($C$5,Rescisoes!$A$3:$A$8,0)),"Nao rescindido") -> Nao rescindido

Sheet Capa
B5: ACME PRE-MOLDADOS INTELIGENTES LTDA (DADOS FICTICIOS)
B6: Controle de Folha de Pagamento - Consolidado RH
B7: Competencia: 05/2026 (fictício)
B9: Abas do workbook
B10: Ficha_Funcionario | D10: Consulta individual: selecione o codigo e veja tudo vinculado
B11: Funcionarios | D11: Cadastro completo (fonte de todos os vinculos)
B12: Liquidos | D12: Valores liquidos pagos por funcionario (Normal Principal/Quinzena/Extra)
B13: Horas_Extras | D13: Horas extras trabalhadas e valores
B14: Faltas / Atestados | D14: Absenteismo por funcionario
B15: Faltas_Detalhado | D15: Movimentos de falta por rubrica
B16: Rescisoes | D16: Rescisoes calculadas no periodo
B17: Rubricas_Folha | D17: Proventos/descontos por departamento e rubrica
B18: Resumo_Departamento | D18: Totais por departamento
B19: Resumo_Geral | D19: KPIs consolidados (formulas)
B22: AVISO: todos os dados neste arquivo sao ficticios, gerados para fins de demonstracao/portfolio.

Sheet Funcionarios
A1: ACME - Cadastro de Funcionarios
A2: Codigo | B2: Nome | C2: Cargo | D2: Admissao | E2: Salario | F2: Servico | G2: Departamento | H2: C_de_Custo | I2: Nascimento | J2: Sexo
A3: 263 | B3: JOAO CAVALCANTE CASTRO FILHO | C3: Assistente Administrativo | D3: 2015-05-11 | E3: 2470 | F3: 1 | G3: Administracao - Fabrica | H3: Fabrica ACME | I3: 1966-05-04 | J3: Masculino
A4: 155 | B4: LEANDRO CORREIA XAVIER | C4: Auxiliar de Producao | D4: 2021-08-10 | E4: 1550 | F4: 1 | G4: Pre-Moldados | H4: Producao ACME | I4: 1977-06-24 | J4: Masculino
A5: 294 | B5: SERGIO CARVALHO MENDES | C5: Operador de Maquinas | D5: 2019-04-06 | E5: 1880 | F5: 2 | G5: Operacional | H5: Operacional ACME | I5: 1969-05-04 | J5: Masculino
A6: 188 | B6: ANA CAVALCANTE SALES | C6: Servente de Obras | D6: 2024-04-20 | E6: 1600 | F6: 2 | G6: ACME_OPERACIONAL_DIARIA | H6: Operacional ACME | I6: 1993-03-14 | J6: Feminino
A7: 247 | B7: SERGIO DE OLIVEIRA REIS | C7: Gerente Administrativo | D7: 2024-09-19 | E7: 9065 | F7: 2 | G7: ACME_ADM DA FABRICA | H7: Fabrica ACME | I7: 1969-07-13 | J7: Masculino
A8: 171 | B8: CRISTINA RIBEIRO PINTO | C8: Operador de Maquinas | D8: 2022-08-31 | E8: 2360 | F8: 1 | G8: Operacional | H8: Operacional ACME | I8: 1994-01-26 | J8: Feminino
A9: 255 | B9: MARCELO CAVALCANTE DIAS MONTEIRO | C9: Supervisor de Producao | D9: 2017-06-18 | E9: 4670 | F9: 2 | G9: ACME_ADM DA FABRICA | H9: Fabrica ACME | I9: 1995-09-17 | J9: Masculino
A10: 296 | B10: RICARDO DOS SANTOS MENDES | C10: Auxiliar Administrativo | D10: 2021-05-12 | E10: 2050 | F10: 2 | G10: Administracao - Fabrica | H10: Fabrica ACME | I10: 2004-04-24 | J10: Masculino
A11: 154 | B11: AMANDA TEIXEIRA SALES FILHO | C11: Operador de Maquinas | D11: 2019-10-21 | E11: 2400 | F11: 2 | G11: Operacional | H11: Operacional ACME | I11: 2005-04-10 | J11: Feminino
A12: 192 | B12: ANTONIO ARAUJO GUIMARAES REIS | C12: Auxiliar Administrativo | D12: 2023-11-19 | E12: 1875 | F12: 2 | G12: Administracao - Fabrica | H12: Fabrica ACME | I12: 1995-07-12 | J12: Masculino
A13: 252 | B13: GUSTAVO MARTINS FARIAS | C13: Supervisor de Producao | D13: 2024-08-26 | E13: 5150 | F13: 1 | G13: Pre-Moldados | H13: Producao ACME | I13: 1965-07-08 | J13: Masculino
A14: 274 | B14: DEBORA TEIXEIRA MENDES BATISTA | C14: Servente de Obras | D14: 2023-02-05 | E14: 1420 | F14: 2 | G14: Apoio a Producao | H14: Producao ACME | I14: 2004-04-15 | J14: Feminino
... A38: 106 | B38: GUSTAVO COSTA CASTRO | C38: Assistente Administrativo | D38: 2019-06-26 | E38: 2515 | F38: 2 | G38: ACME_ADM DA FABRICA | H38: Fabrica ACME | I38: 1995-06-26 | J38: Masculino

Sheet Liquidos
A1: ACME - Valores Liquidos Pagos
A2: Departamento_Num | B2: Departamento | C2: Codigo | D2: Nome | E2: Valor | F2: Data_Pagamento | G2: Tipo Folha | H2: Cargo (vinculo) | I2: C. de Custo (vinculo)
A3: 1 | B3: Administracao - Fabrica | C3: 263 | D3: JOAO CAVALCANTE CASTRO FILHO | E3: 1414.49 | F3: 2026-06-01 | G3: Normal Principal | H3: =IFERROR(INDEX(Funcionarios!$C$3:$C$38,MATCH($C3,Funcionarios!$A$3:$A$38,0)),"") -> Assistente Administrativo | I3: =IFERROR(INDEX(Funcionarios!$H$3:$H$38,MATCH($C3,Funcionarios!$A$3:$A$38,0)),"") -> Fabrica ACME
A4: 2 | B4: Pre-Moldados | C4: 155 | D4: LEANDRO CORREIA XAVIER | E4: 868.87 | F4: 2026-06-01 | G4: Normal Principal | H4: =IFERROR(INDEX(Funcionarios!$C$3:$C$38,MATCH($C4,Funcionarios!$A$3:$A$38,0)),"") -> Auxiliar de Producao | I4: =IFERROR(INDEX(Funcionarios!$H$3:$H$38,MATCH($C4,Funcionarios!$A$3:$A$38,0)),"") -> Producao ACME
A5: 3 | B5: Operacional | C5: 294 | D5: SERGIO CARVALHO MENDES | E5: 1119.66 | F5: 2026-06-01 | G5: Normal Principal | H5: =IFERROR(INDEX(Funcionarios!$C$3:$C$38,MATCH($C5,Funcionarios!$A$3:$A$38,0)),"") -> Operador de Maquinas | I5: =IFERROR(INDEX(Funcionarios!$H$3:$H$38,MATCH($C5,Funcionarios!$A$3:$A$38,0)),"") -> Operacional ACME
A6: 4 | B6: ACME_OPERACIONAL_DIARIA | C6: 188 | D6: ANA CAVALCANTE SALES | E6: 888.11 | F6: 2026-06-01 | G6: Normal Principal | H6: =IFERROR(INDEX(Funcionarios!$C$3:$C$38,MATCH($C6,Funcionarios!$A$3:$A$38,0)),"") -> Servente de Obras | I6: =IFERROR(INDEX(Funcionarios!$H$3:$H$38,MATCH($C6,Funcionarios!$A$3:$A$38,0)),"") -> Operacional ACME
A7: 5 | B7: ACME_ADM DA FABRICA | C7: 247 | D7: SERGIO DE OLIVEIRA REIS | E7: 5325.79 | F7: 2026-06-01 | G7: Normal Principal | H7: =IFERROR(INDEX(Funcionarios!$C$3:$C$38,MATCH($C7,Funcionarios!$A$3:$A$38,0)),"") -> Gerente Administrativo | I7: =IFERROR(INDEX(Funcionarios!$H$3:$H$38,MATCH($C7,Funcionarios!$A$3:$A$38,0)),"") -> Fabrica ACME
A8: 3 | B8: Operacional | C8: 171 | D8: CRISTINA RIBEIRO PINTO | E8: 1358.41 | F8: 2026-06-01 | G8: Normal Principal | H8: =IFERROR(INDEX(Funcionarios!$C$3:$C$38,MATCH($C8,Funcionarios!$A$3:$A$38,0)),"") -> Operador de Maquinas | I8: =IFERROR(INDEX(Funcionarios!$H$3:$H$38,MATCH($C8,Funcionarios!$A$3:$A$38,0)),"") -> Operacional ACME
A9: 5 | B9: ACME_ADM DA FABRICA | C9: 255 | D9: MARCELO CAVALCANTE DIAS MONTEIRO | E9: 2587.46 | F9: 2026-06-01 | G9: Normal Principal | H9: =IFERROR(INDEX(Funcionarios!$C$3:$C$38,MATCH($C9,Funcionarios!$A$3:$A$38,0)),"") -> Supervisor de Producao | I9: =IFERROR(INDEX(Funcionarios!$H$3:$H$38,MATCH($C9,Funcionarios!$A$3:$A$38,0)),"") -> Fabrica ACME
A10: 1 | B10: Administracao - Fabrica | C10: 296 | D10: RICARDO DOS SANTOS MENDES | E10: 1200.32 | F10: 2026-06-01 | G10: Normal Principal | H10: =IFERROR(INDEX(Funcionarios!$C$3:$C$38,MATCH($C10,Funcionarios!$A$3:$A$38,0)),"") -> Auxiliar Administrativo | I10: =IFERROR(INDEX(Funcionarios!$H$3:$H$38,MATCH($C10,Funcionarios!$A$3:$A$38,0)),"") -> Fabrica ACME
A11: 3 | B11: Operacional | C11: 154 | D11: AMANDA TEIXEIRA SALES FILHO | E11: 1326.3 | F11: 2026-06-01 | G11: Normal Principal | H11: =IFERROR(INDEX(Funcionarios!$C$3:$C$38,MATCH($C11,Funcionarios!$A$3:$A$38,0)),"") -> Operador de Maquinas | I11: =IFERROR(INDEX(Funcionarios!$H$3:$H$38,MATCH($C11,Funcionarios!$A$3:$A$38,0)),"") -> Operacional ACME
A12: 1 | B12: Administracao - Fabrica | C12: 192 | D12: ANTONIO ARAUJO GUIMARAES REIS | E12: 1088.17 | F12: 2026-06-01 | G12: Normal Principal | H12: =IFERROR(INDEX(Funcionarios!$C$3:$C$38,MATCH($C12,Funcionarios!$A$3:$A$38,0)),"") -> Auxiliar Administrativo | I12: =IFERROR(INDEX(Funcionarios!$H$3:$H$38,MATCH($C12,Funcionarios!$A$3:$A$38,0)),"") -> Fabrica ACME
A13: 2 | B13: Pre-Moldados | C13: 252 | D13: GUSTAVO MARTINS FARIAS | E13: 2857.68 | F13: 2026-06-01 | G13: Normal Principal | H13: =IFERROR(INDEX(Funcionarios!$C$3:$C$38,MATCH($C13,Funcionarios!$A$3:$A$38,0)),"") -> Supervisor de Producao | I13: =IFERROR(INDEX(Funcionarios!$H$3:$H$38,MATCH($C13,Funcionarios!$A$3:$A$38,0)),"") -> Producao ACME
A14: 6 | B14: Apoio a Producao | C14: 274 | D14: DEBORA TEIXEIRA MENDES BATISTA | E14: 790.02 | F14: 2026-06-01 | G14: Normal Principal | H14: =IFERROR(INDEX(Funcionarios!$C$3:$C$38,MATCH($C14,Funcionarios!$A$3:$A$38,0)),"") -> Servente de Obras | I14: =IFERROR(INDEX(Funcionarios!$H$3:$H$38,MATCH($C14,Funcionarios!$A$3:$A$38,0)),"") -> Producao ACME
... A86: 5 | B86: ACME_ADM DA FABRICA | C86: 106 | D86: GUSTAVO COSTA CASTRO | E86: 375.21 | F86: 2026-06-01 | G86: Extra | H86: =IFERROR(INDEX(Funcionarios!$C$3:$C$38,MATCH($C86,Funcionarios!$A$3:$A$38,0)),"") -> Assistente Administrativo | I86: =IFERROR(INDEX(Funcionarios!$H$3:$H$38,MATCH($C86,Funcionarios!$A$3:$A$38,0)),"") -> Fabrica ACME

Sheet Horas_Extras
A1: ACME - Horas Extras
A2: Departamento_Num | B2: Departamento | C2: Codigo | D2: Nome | E2: Rubrica_Num | F2: Rubrica_Nome | G2: Competencia | H2: Valor_Calculado | I2: Horas | J2: Tipo_Movimento | K2: Unidade | L2: Tipo Folha | M2: Cargo (vinculo) | N2: C. de Custo (vinculo)
A3: 6 | B3: Apoio a Producao | C3: 166 | D3: RENATO MOREIRA MENDES MONTEIRO | E3: 150 | F3: HORAS EXTRAS 100% | G3: 05/2026 | H3: 61.21 | I3: 3.82 | J3: P | K3: Horas | L3: Normal | M3: =IFERROR(INDEX(Funcionarios!$C$3:$C$38,MATCH($C3,Funcionarios!$A$3:$A$38,0)),"") -> Almoxarife | N3: =IFERROR(INDEX(Funcionarios!$H$3:$H$38,MATCH($C3,Funcionarios!$A$3:$A$38,0)),"") -> Producao ACME
A4: 6 | B4: Apoio a Producao | C4: 166 | D4: RENATO MOREIRA MENDES MONTEIRO | E4: 150 | F4: HORAS EXTRAS 100% | G4: 05/2026 | H4: 199.32 | I4: 12.44 | J4: P | K4: Horas | L4: Extra | M4: =IFERROR(INDEX(Funcionarios!$C$3:$C$38,MATCH($C4,Funcionarios!$A$3:$A$38,0)),"") -> Almoxarife | N4: =IFERROR(INDEX(Funcionarios!$H$3:$H$38,MATCH($C4,Funcionarios!$A$3:$A$38,0)),"") -> Producao ACME
A5: 5 | B5: ACME_ADM DA FABRICA | C5: 106 | D5: GUSTAVO COSTA CASTRO | E5: 150 | F5: HORAS EXTRAS 100% | G5: 05/2026 | H5: 340.73 | I5: 19.87 | J5: P | K5: Horas | L5: Extra | M5: =IFERROR(INDEX(Funcionarios!$C$3:$C$38,MATCH($C5,Funcionarios!$A$3:$A$38,0)),"") -> Assistente Administrativo | N5: =IFERROR(INDEX(Funcionarios!$H$3:$H$38,MATCH($C5,Funcionarios!$A$3:$A$38,0)),"") -> Fabrica ACME
A6: 4 | B6: ACME_OPERACIONAL_DIARIA | C6: 145 | D6: MARIA FERREIRA MENDES | E6: 150 | F6: HORAS EXTRAS 100% | G6: 05/2026 | H6: 189.06 | I6: 15.07 | J6: P | K6: Horas | L6: Extra | M6: =IFERROR(INDEX(Funcionarios!$C$3:$C$38,MATCH($C6,Funcionarios!$A$3:$A$38,0)),"") -> Auxiliar de Producao | N6: =IFERROR(INDEX(Funcionarios!$H$3:$H$38,MATCH($C6,Funcionarios!$A$3:$A$38,0)),"") -> Operacional ACME
A7: 5 | B7: ACME_ADM DA FABRICA | C7: 255 | D7: MARCELO CAVALCANTE DIAS MONTEIRO | E7: 150 | F7: HORAS EXTRAS 50% | G7: 05/2026 | H7: 129.59 | I7: 4.07 | J7: P | K7: Horas | L7: Normal | M7: =IFERROR(INDEX(Funcionarios!$C$3:$C$38,MATCH($C7,Funcionarios!$A$3:$A$38,0)),"") -> Supervisor de Producao | N7: =IFERROR(INDEX(Funcionarios!$H$3:$H$38,MATCH($C7,Funcionarios!$A$3:$A$38,0)),"") -> Fabrica ACME
A8: 4 | B8: ACME_OPERACIONAL_DIARIA | C8: 235 | D8: MARCIA NASCIMENTO ROCHA | E8: 150 | F8: HORAS EXTRAS NOTURNAS | G8: 05/2026 | H8: 93.37 | I8: 7.87 | J8: P | K8: Horas | L8: Normal | M8: =IFERROR(INDEX(Funcionarios!$C$3:$C$38,MATCH($C8,Funcionarios!$A$3:$A$38,0)),"") -> Auxiliar de Producao | N8: =IFERROR(INDEX(Funcionarios!$H$3:$H$38,MATCH($C8,Funcionarios!$A$3:$A$38,0)),"") -> Operacional ACME
A9: 4 | B9: ACME_OPERACIONAL_DIARIA | C9: 235 | D9: MARCIA NASCIMENTO ROCHA | E9: 150 | F9: HORAS EXTRAS NOTURNAS | G9: 05/2026 | H9: 17.91 | I9: 1.51 | J9: P | K9: Horas | L9: Extra | M9: =IFERROR(INDEX(Funcionarios!$C$3:$C$38,MATCH($C9,Funcionarios!$A$3:$A$38,0)),"") -> Auxiliar de Producao | N9: =IFERROR(INDEX(Funcionarios!$H$3:$H$38,MATCH($C9,Funcionarios!$A$3:$A$38,0)),"") -> Operacional ACME
A10: 1 | B10: Administracao - Fabrica | C10: 208 | D10: EDUARDO ALMEIDA DIAS | E10: 150 | F10: HORAS EXTRAS 100% | G10: 05/2026 | H10: 34.71 | I10: 2.73 | J10: P | K10: Horas | L10: Extra | M10: =IFERROR(INDEX(Funcionarios!$C$3:$C$38,MATCH($C10,Funcionarios!$A$3:$A$38,0)),"") -> Auxiliar de Almoxarifado | N10: =IFERROR(INDEX(Funcionarios!$H$3:$H$38,MATCH($C10,Funcionarios!$A$3:$A$38,0)),"") -> Fabrica ACME
A11: 2 | B11: Pre-Moldados | C11: 228 | D11: LEANDRO SOUZA FREITAS | E11: 150 | F11: HORAS EXTRAS 100% | G11: 05/2026 | H11: 268.3 | I11: 18.26 | J11: P | K11: Horas | L11: Normal | M11: =IFERROR(INDEX(Funcionarios!$C$3:$C$38,MATCH($C11,Funcionarios!$A$3:$A$38,0)),"") -> Soldador | N11: =IFERROR(INDEX(Funcionarios!$H$3:$H$38,MATCH($C11,Funcionarios!$A$3:$A$38,0)),"") -> Producao ACME
A12: 2 | B12: Pre-Moldados | C12: 228 | D12: LEANDRO SOUZA FREITAS | E12: 150 | F12: HORAS EXTRAS NOTURNAS | G12: 05/2026 | H12: 163.39 | I12: 11.12 | J12: P | K12: Horas | L12: Extra | M12: =IFERROR(INDEX(Funcionarios!$C$3:$C$38,MATCH($C12,Funcionarios!$A$3:$A$38,0)),"") -> Soldador | N12: =IFERROR(INDEX(Funcionarios!$H$3:$H$38,MATCH($C12,Funcionarios!$A$3:$A$38,0)),"") -> Producao ACME
A13: 9 | B13: Administracao - Escritorio | C13: 239 | D13: FERNANDO CARDOSO PEIXOTO FILHO | E13: 150 | F13: HORAS EXTRAS 50% | G13: 05/2026 | H13: 307.74 | I13: 19.71 | J13: P | K13: Horas | L13: Normal | M13: =IFERROR(INDEX(Funcionarios!$C$3:$C$38,MATCH($C13,Funcionarios!$A$3:$A$38,0)),"") -> Assistente Administrativo | N13: =IFERROR(INDEX(Funcionarios!$H$3:$H$38,MATCH($C13,Funcionarios!$A$3:$A$38,0)),"") -> Escritorio ACME
A14: 9 | B14: Administracao - Escritorio | C14: 239 | D14: FERNANDO CARDOSO PEIXOTO FILHO | E14: 150 | F14: HORAS EXTRAS NOTURNAS | G14: 05/2026 | H14: 258.41 | I14: 16.55 | J14: P | K14: Horas | L14: Extra | M14: =IFERROR(INDEX(Funcionarios!$C$3:$C$38,MATCH($C14,Funcionarios!$A$3:$A$38,0)),"") -> Assistente Administrativo | N14: =IFERROR(INDEX(Funcionarios!$H$3:$H$38,MATCH($C14,Funcionarios!$A$3:$A$38,0)),"") -> Escritorio ACME
... A32: 5 | B32: ACME_ADM DA FABRICA | C32: 158 | D32: CARLOS COSTA JUNIOR | E32: 150 | F32: HORAS EXTRAS 100% | G32: 05/2026 | H32: 457.37 | I32: 15.51 | J32: P | K32: Horas | L32: Extra | M32: =IFERROR(INDEX(Funcionarios!$C$3:$C$38,MATCH($C32,Funcionarios!$A$3:$A$38,0)),"") -> Supervisor de Producao | N32: =IFERROR(INDEX(Funcionarios!$H$3:$H$38,MATCH($C32,Funcionarios!$A$3:$A$38,0)),"") -> Fabrica ACME

Sheet Faltas
A1: ACME - Faltas
A2: Funcionario | B2: Previstas_h | C2: Trabalhadas_h | D2: Ausencias_h | E2: Pct_Ausencias | F2: Tipo | G2: Codigo (vinculo) | H2: Departamento (vinculo) | I2: Cargo (vinculo)
A3: JOAO CAVALCANTE CASTRO FILHO | B3: 220 | C3: 214.97 | D3: 5.03 | E3: 0.0229 | F3: Faltas | G3: =IFERROR(INDEX(Funcionarios!$A$3:$A$38,MATCH($A3,Funcionarios!$B$3:$B$38,0)),"") -> 263 | H3: =IFERROR(INDEX(Funcionarios!$G$3:$G$38,MATCH($A3,Funcionarios!$B$3:$B$38,0)),"") -> Administracao - Fabrica | I3: =IFERROR(INDEX(Funcionarios!$C$3:$C$38,MATCH($A3,Funcionarios!$B$3:$B$38,0)),"") -> Assistente Administrativo
A4: LEANDRO CORREIA XAVIER | B4: 220 | C4: 209.08 | D4: 10.92 | E4: 0.0496 | F4: Faltas | G4: =IFERROR(INDEX(Funcionarios!$A$3:$A$38,MATCH($A4,Funcionarios!$B$3:$B$38,0)),"") -> 155 | H4: =IFERROR(INDEX(Funcionarios!$G$3:$G$38,MATCH($A4,Funcionarios!$B$3:$B$38,0)),"") -> Pre-Moldados | I4: =IFERROR(INDEX(Funcionarios!$C$3:$C$38,MATCH($A4,Funcionarios!$B$3:$B$38,0)),"") -> Auxiliar de Producao
A5: SERGIO CARVALHO MENDES | B5: 220 | C5: 220 | D5: 0 | E5: 0 | F5: Faltas | G5: =IFERROR(INDEX(Funcionarios!$A$3:$A$38,MATCH($A5,Funcionarios!$B$3:$B$38,0)),"") -> 294 | H5: =IFERROR(INDEX(Funcionarios!$G$3:$G$38,MATCH($A5,Funcionarios!$B$3:$B$38,0)),"") -> Operacional | I5: =IFERROR(INDEX(Funcionarios!$C$3:$C$38,MATCH($A5,Funcionarios!$B$3:$B$38,0)),"") -> Operador de Maquinas
A6: ANA CAVALCANTE SALES | B6: 220 | C6: 220 | D6: 0 | E6: 0 | F6: Faltas | G6: =IFERROR(INDEX(Funcionarios!$A$3:$A$38,MATCH($A6,Funcionarios!$B$3:$B$38,0)),"") -> 188 | H6: =IFERROR(INDEX(Funcionarios!$G$3:$G$38,MATCH($A6,Funcionarios!$B$3:$B$38,0)),"") -> ACME_OPERACIONAL_DIARIA | I6: =IFERROR(INDEX(Funcionarios!$C$3:$C$38,MATCH($A6,Funcionarios!$B$3:$B$38,0)),"") -> Servente de Obras
A7: SERGIO DE OLIVEIRA REIS | B7: 220 | C7: 220 | D7: 0 | E7: 0 | F7: Faltas | G7: =IFERROR(INDEX(Funcionarios!$A$3:$A$38,MATCH($A7,Funcionarios!$B$3:$B$38,0)),"") -> 247 | H7: =IFERROR(INDEX(Funcionarios!$G$3:$G$38,MATCH($A7,Funcionarios!$B$3:$B$38,0)),"") -> ACME_ADM DA FABRICA | I7: =IFERROR(INDEX(Funcionarios!$C$3:$C$38,MATCH($A7,Funcionarios!$B$3:$B$38,0)),"") -> Gerente Administrativo
A8: CRISTINA RIBEIRO PINTO | B8: 220 | C8: 220 | D8: 0 | E8: 0 | F8: Faltas | G8: =IFERROR(INDEX(Funcionarios!$A$3:$A$38,MATCH($A8,Funcionarios!$B$3:$B$38,0)),"") -> 171 | H8: =IFERROR(INDEX(Funcionarios!$G$3:$G$38,MATCH($A8,Funcionarios!$B$3:$B$38,0)),"") -> Operacional | I8: =IFERROR(INDEX(Funcionarios!$C$3:$C$38,MATCH($A8,Funcionarios!$B$3:$B$38,0)),"") -> Operador de Maquinas
A9: MARCELO CAVALCANTE DIAS MONTEIRO | B9: 220 | C9: 220 | D9: 0 | E9: 0 | F9: Faltas | G9: =IFERROR(INDEX(Funcionarios!$A$3:$A$38,MATCH($A9,Funcionarios!$B$3:$B$38,0)),"") -> 255 | H9: =IFERROR(INDEX(Funcionarios!$G$3:$G$38,MATCH($A9,Funcionarios!$B$3:$B$38,0)),"") -> ACME_ADM DA FABRICA | I9: =IFERROR(INDEX(Funcionarios!$C$3:$C$38,MATCH($A9,Funcionarios!$B$3:$B$38,0)),"") -> Supervisor de Producao
A10: RICARDO DOS SANTOS MENDES | B10: 220 | C10: 220 | D10: 0 | E10: 0 | F10: Faltas | G10: =IFERROR(INDEX(Funcionarios!$A$3:$A$38,MATCH($A10,Funcionarios!$B$3:$B$38,0)),"") -> 296 | H10: =IFERROR(INDEX(Funcionarios!$G$3:$G$38,MATCH($A10,Funcionarios!$B$3:$B$38,0)),"") -> Administracao - Fabrica | I10: =IFERROR(INDEX(Funcionarios!$C$3:$C$38,MATCH($A10,Funcionarios!$B$3:$B$38,0)),"") -> Auxiliar Administrativo
A11: AMANDA TEIXEIRA SALES FILHO | B11: 220 | C11: 220 | D11: 0 | E11: 0 | F11: Faltas | G11: =IFERROR(INDEX(Funcionarios!$A$3:$A$38,MATCH($A11,Funcionarios!$B$3:$B$38,0)),"") -> 154 | H11: =IFERROR(INDEX(Funcionarios!$G$3:$G$38,MATCH($A11,Funcionarios!$B$3:$B$38,0)),"") -> Operacional | I11: =IFERROR(INDEX(Funcionarios!$C$3:$C$38,MATCH($A11,Funcionarios!$B$3:$B$38,0)),"") -> Operador de Maquinas
A12: ANTONIO ARAUJO GUIMARAES REIS | B12: 220 | C12: 220 | D12: 0 | E12: 0 | F12: Faltas | G12: =IFERROR(INDEX(Funcionarios!$A$3:$A$38,MATCH($A12,Funcionarios!$B$3:$B$38,0)),"") -> 192 | H12: =IFERROR(INDEX(Funcionarios!$G$3:$G$38,MATCH($A12,Funcionarios!$B$3:$B$38,0)),"") -> Administracao - Fabrica | I12: =IFERROR(INDEX(Funcionarios!$C$3:$C$38,MATCH($A12,Funcionarios!$B$3:$B$38,0)),"") -> Auxiliar Administrativo
A13: GUSTAVO MARTINS FARIAS | B13: 220 | C13: 220 | D13: 0 | E13: 0 | F13: Faltas | G13: =IFERROR(INDEX(Funcionarios!$A$3:$A$38,MATCH($A13,Funcionarios!$B$3:$B$38,0)),"") -> 252 | H13: =IFERROR(INDEX(Funcionarios!$G$3:$G$38,MATCH($A13,Funcionarios!$B$3:$B$38,0)),"") -> Pre-Moldados | I13: =IFERROR(INDEX(Funcionarios!$C$3:$C$38,MATCH($A13,Funcionarios!$B$3:$B$38,0)),"") -> Supervisor de Producao
A14: DEBORA TEIXEIRA MENDES BATISTA | B14: 220 | C14: 214.72 | D14: 5.28 | E14: 0.024 | F14: Faltas | G14: =IFERROR(INDEX(Funcionarios!$A$3:$A$38,MATCH($A14,Funcionarios!$B$3:$B$38,0)),"") -> 274 | H14: =IFERROR(INDEX(Funcionarios!$G$3:$G$38,MATCH($A14,Funcionarios!$B$3:$B$38,0)),"") -> Apoio a Producao | I14: =IFERROR(INDEX(Funcionarios!$C$3:$C$38,MATCH($A14,Funcionarios!$B$3:$B$38,0)),"") -> Servente de Obras
... A38: GUSTAVO COSTA CASTRO | B38: 220 | C38: 220 | D38: 0 | E38: 0 | F38: Faltas | G38: =IFERROR(INDEX(Funcionarios!$A$3:$A$38,MATCH($A38,Funcionarios!$B$3:$B$38,0)),"") -> 106 | H38: =IFERROR(INDEX(Funcionarios!$G$3:$G$38,MATCH($A38,Funcionarios!$B$3:$B$38,0)),"") -> ACME_ADM DA FABRICA | I38: =IFERROR(INDEX(Funcionarios!$C$3:$C$38,MATCH($A38,Funcionarios!$B$3:$B$38,0)),"") -> Assistente Administrativo

Sheet Atestados
A1: ACME - Atestados
A2: Funcionario | B2: Previstas_h | C2: Trabalhadas_h | D2: Ausencias_h | E2: Pct_Ausencias | F2: Tipo | G2: Codigo (vinculo) | H2: Departamento (vinculo) | I2: Cargo (vinculo)
A3: JOAO CAVALCANTE CASTRO FILHO | B3: 220 | C3: 220 | D3: 0 | E3: 0 | F3: Atestados | G3: =IFERROR(INDEX(Funcionarios!$A$3:$A$38,MATCH($A3,Funcionarios!$B$3:$B$38,0)),"") -> 263 | H3: =IFERROR(INDEX(Funcionarios!$G$3:$G$38,MATCH($A3,Funcionarios!$B$3:$B$38,0)),"") -> Administracao - Fabrica | I3: =IFERROR(INDEX(Funcionarios!$C$3:$C$38,MATCH($A3,Funcionarios!$B$3:$B$38,0)),"") -> Assistente Administrativo
A4: LEANDRO CORREIA XAVIER | B4: 220 | C4: 220 | D4: 0 | E4: 0 | F4: Atestados | G4: =IFERROR(INDEX(Funcionarios!$A$3:$A$38,MATCH($A4,Funcionarios!$B$3:$B$38,0)),"") -> 155 | H4: =IFERROR(INDEX(Funcionarios!$G$3:$G$38,MATCH($A4,Funcionarios!$B$3:$B$38,0)),"") -> Pre-Moldados | I4: =IFERROR(INDEX(Funcionarios!$C$3:$C$38,MATCH($A4,Funcionarios!$B$3:$B$38,0)),"") -> Auxiliar de Producao
A5: SERGIO CARVALHO MENDES | B5: 220 | C5: 220 | D5: 0 | E5: 0 | F5: Atestados | G5: =IFERROR(INDEX(Funcionarios!$A$3:$A$38,MATCH($A5,Funcionarios!$B$3:$B$38,0)),"") -> 294 | H5: =IFERROR(INDEX(Funcionarios!$G$3:$G$38,MATCH($A5,Funcionarios!$B$3:$B$38,0)),"") -> Operacional | I5: =IFERROR(INDEX(Funcionarios!$C$3:$C$38,MATCH($A5,Funcionarios!$B$3:$B$38,0)),"") -> Operador de Maquinas
A6: ANA CAVALCANTE SALES | B6: 220 | C6: 213.29 | D6: 6.71 | E6: 0.0305 | F6: Atestados | G6: =IFERROR(INDEX(Funcionarios!$A$3:$A$38,MATCH($A6,Funcionarios!$B$3:$B$38,0)),"") -> 188 | H6: =IFERROR(INDEX(Funcionarios!$G$3:$G$38,MATCH($A6,Funcionarios!$B$3:$B$38,0)),"") -> ACME_OPERACIONAL_DIARIA | I6: =IFERROR(INDEX(Funcionarios!$C$3:$C$38,MATCH($A6,Funcionarios!$B$3:$B$38,0)),"") -> Servente de Obras
A7: SERGIO DE OLIVEIRA REIS | B7: 220 | C7: 220 | D7: 0 | E7: 0 | F7: Atestados | G7: =IFERROR(INDEX(Funcionarios!$A$3:$A$38,MATCH($A7,Funcionarios!$B$3:$B$38,0)),"") -> 247 | H7: =IFERROR(INDEX(Funcionarios!$G$3:$G$38,MATCH($A7,Funcionarios!$B$3:$B$38,0)),"") -> ACME_ADM DA FABRICA | I7: =IFERROR(INDEX(Funcionarios!$C$3:$C$38,MATCH($A7,Funcionarios!$B$3:$B$38,0)),"") -> Gerente Administrativo
A8: CRISTINA RIBEIRO PINTO | B8: 220 | C8: 220 | D8: 0 | E8: 0 | F8: Atestados | G8: =IFERROR(INDEX(Funcionarios!$A$3:$A$38,MATCH($A8,Funcionarios!$B$3:$B$38,0)),"") -> 171 | H8: =IFERROR(INDEX(Funcionarios!$G$3:$G$38,MATCH($A8,Funcionarios!$B$3:$B$38,0)),"") -> Operacional | I8: =IFERROR(INDEX(Funcionarios!$C$3:$C$38,MATCH($A8,Funcionarios!$B$3:$B$38,0)),"") -> Operador de Maquinas
A9: MARCELO CAVALCANTE DIAS MONTEIRO | B9: 220 | C9: 218.54 | D9: 1.46 | E9: 0.0066 | F9: Atestados | G9: =IFERROR(INDEX(Funcionarios!$A$3:$A$38,MATCH($A9,Funcionarios!$B$3:$B$38,0)),"") -> 255 | H9: =IFERROR(INDEX(Funcionarios!$G$3:$G$38,MATCH($A9,Funcionarios!$B$3:$B$38,0)),"") -> ACME_ADM DA FABRICA | I9: =IFERROR(INDEX(Funcionarios!$C$3:$C$38,MATCH($A9,Funcionarios!$B$3:$B$38,0)),"") -> Supervisor de Producao
A10: RICARDO DOS SANTOS MENDES | B10: 220 | C10: 220 | D10: 0 | E10: 0 | F10: Atestados | G10: =IFERROR(INDEX(Funcionarios!$A$3:$A$38,MATCH($A10,Funcionarios!$B$3:$B$38,0)),"") -> 296 | H10: =IFERROR(INDEX(Funcionarios!$G$3:$G$38,MATCH($A10,Funcionarios!$B$3:$B$38,0)),"") -> Administracao - Fabrica | I10: =IFERROR(INDEX(Funcionarios!$C$3:$C$38,MATCH($A10,Funcionarios!$B$3:$B$38,0)),"") -> Auxiliar Administrativo
A11: AMANDA TEIXEIRA SALES FILHO | B11: 220 | C11: 217.11 | D11: 2.89 | E11: 0.0131 | F11: Atestados | G11: =IFERROR(INDEX(Funcionarios!$A$3:$A$38,MATCH($A11,Funcionarios!$B$3:$B$38,0)),"") -> 154 | H11: =IFERROR(INDEX(Funcionarios!$G$3:$G$38,MATCH($A11,Funcionarios!$B$3:$B$38,0)),"") -> Operacional | I11: =IFERROR(INDEX(Funcionarios!$C$3:$C$38,MATCH($A11,Funcionarios!$B$3:$B$38,0)),"") -> Operador de Maquinas
A12: ANTONIO ARAUJO GUIMARAES REIS | B12: 220 | C12: 211.97 | D12: 8.03 | E12: 0.0365 | F12: Atestados | G12: =IFERROR(INDEX(Funcionarios!$A$3:$A$38,MATCH($A12,Funcionarios!$B$3:$B$38,0)),"") -> 192 | H12: =IFERROR(INDEX(Funcionarios!$G$3:$G$38,MATCH($A12,Funcionarios!$B$3:$B$38,0)),"") -> Administracao - Fabrica | I12: =IFERROR(INDEX(Funcionarios!$C$3:$C$38,MATCH($A12,Funcionarios!$B$3:$B$38,0)),"") -> Auxiliar Administrativo
A13: GUSTAVO MARTINS FARIAS | B13: 220 | C13: 220 | D13: 0 | E13: 0 | F13: Atestados | G13: =IFERROR(INDEX(Funcionarios!$A$3:$A$38,MATCH($A13,Funcionarios!$B$3:$B$38,0)),"") -> 252 | H13: =IFERROR(INDEX(Funcionarios!$G$3:$G$38,MATCH($A13,Funcionarios!$B$3:$B$38,0)),"") -> Pre-Moldados | I13: =IFERROR(INDEX(Funcionarios!$C$3:$C$38,MATCH($A13,Funcionarios!$B$3:$B$38,0)),"") -> Supervisor de Producao
A14: DEBORA TEIXEIRA MENDES BATISTA | B14: 220 | C14: 220 | D14: 0 | E14: 0 | F14: Atestados | G14: =IFERROR(INDEX(Funcionarios!$A$3:$A$38,MATCH($A14,Funcionarios!$B$3:$B$38,0)),"") -> 274 | H14: =IFERROR(INDEX(Funcionarios!$G$3:$G$38,MATCH($A14,Funcionarios!$B$3:$B$38,0)),"") -> Apoio a Producao | I14: =IFERROR(INDEX(Funcionarios!$C$3:$C$38,MATCH($A14,Funcionarios!$B$3:$B$38,0)),"") -> Servente de Obras
... A38: GUSTAVO COSTA CASTRO | B38: 220 | C38: 218.45 | D38: 1.55 | E38: 0.007 | F38: Atestados | G38: =IFERROR(INDEX(Funcionarios!$A$3:$A$38,MATCH($A38,Funcionarios!$B$3:$B$38,0)),"") -> 106 | H38: =IFERROR(INDEX(Funcionarios!$G$3:$G$38,MATCH($A38,Funcionarios!$B$3:$B$38,0)),"") -> ACME_ADM DA FABRICA | I38: =IFERROR(INDEX(Funcionarios!$C$3:$C$38,MATCH($A38,Funcionarios!$B$3:$B$38,0)),"") -> Assistente Administrativo

Sheet Faltas_Detalhado
A1: ACME - Faltas Detalhado
A2: Departamento_Num | B2: Departamento | C2: Codigo | D2: Nome | E2: Rubrica_Num | F2: Rubrica_Nome | G2: Competencia | H2: Valor_Calculado | I2: Horas | J2: Tipo_Movimento | K2: Unidade
A3: 2 | B3: Pre-Moldados | C3: 194 | D3: JULIANA ALMEIDA PEIXOTO | E3: 40 | F3: HORAS FALTAS | G3: 05/2026 | H3: 62.73 | I3: 5.91 | J3: D | K3: Horas
A4: 3 | B4: Operacional | C4: 130 | D4: RICARDO DE OLIVEIRA MENDES PEIXOTO | E4: 40 | F4: HORAS FALTAS | G4: 05/2026 | H4: 51.31 | I4: 7.95 | J4: D | K4: Horas
A5: 6 | B5: Apoio a Producao | C5: 166 | D5: RENATO MOREIRA MENDES MONTEIRO | E5: 40 | F5: HORAS FALTAS | G5: 05/2026 | H5: 61.53 | I5: 5.76 | J5: D | K5: Horas
A6: 1 | B6: Administracao - Fabrica | C6: 192 | D6: ANTONIO ARAUJO GUIMARAES REIS | E6: 40 | F6: FALTAS INJUSTIFICADAS | G6: 05/2026 | H6: 92.73 | I6: 10.88 | J6: D | K6: Horas
A7: 9 | B7: Administracao - Escritorio | C7: 239 | D7: FERNANDO CARDOSO PEIXOTO FILHO | E7: 40 | F7: HORAS FALTAS | G7: 05/2026 | H7: 33 | I7: 3.17 | J7: D | K7: Horas
A8: 2 | B8: Pre-Moldados | C8: 197 | D8: GUSTAVO LIMA SALES | E8: 40 | F8: HORAS FALTAS | G8: 05/2026 | H8: 20.24 | I8: 2.93 | J8: D | K8: Horas
A9: 2 | B9: Pre-Moldados | C9: 252 | D9: GUSTAVO MARTINS FARIAS | E9: 40 | F9: FALTAS INJUSTIFICADAS | G9: 05/2026 | H9: 195.47 | I9: 8.35 | J9: D | K9: Horas
A10: 3 | B10: Operacional | C10: 294 | D10: SERGIO CARVALHO MENDES | E10: 40 | F10: FALTAS INJUSTIFICADAS | G10: 05/2026 | H10: 136.04 | I10: 15.92 | J10: D | K10: Horas

Sheet Rescisoes
A1: ACME - Rescisoes
A2: Codigo | B2: Empregado | C2: Admissao | D2: Aviso | E2: Demissao | F2: Saldo_FGTS | G2: Salario | H2: Proventos | I2: Descontos | J2: Liquido | K2: FGTS_Rescisorio | L2: Motivo_Demissao | M2: Departamento (vinculo) | N2: Cargo (vinculo)
A3: 158 | B3: CARLOS COSTA JUNIOR | C3: 2021-01-17 | D3: 2026-05-08 | E3: 2026-05-09 | F3: 207.17 | G3: 4325 | H3: 2142.11 | I3: 727.97 | J3: 1414.14 | K3: 346 | L3: Dispensa sem justa causa | M3: =IFERROR(INDEX(Funcionarios!$G$3:$G$38,MATCH($A3,Funcionarios!$A$3:$A$38,0)),"") -> ACME_ADM DA FABRICA | N3: =IFERROR(INDEX(Funcionarios!$C$3:$C$38,MATCH($A3,Funcionarios!$A$3:$A$38,0)),"") -> Supervisor de Producao
A4: 154 | B4: AMANDA TEIXEIRA SALES FILHO | C4: 2019-10-21 | D4: 2026-04-26 | E4: 2026-05-10 | F4: 136.75 | G4: 2400 | H4: 1380.05 | I4: 312.84 | J4: 1067.21 | K4: 192 | L4: Pedido de Demissao | M4: =IFERROR(INDEX(Funcionarios!$G$3:$G$38,MATCH($A4,Funcionarios!$A$3:$A$38,0)),"") -> Operacional | N4: =IFERROR(INDEX(Funcionarios!$C$3:$C$38,MATCH($A4,Funcionarios!$A$3:$A$38,0)),"") -> Operador de Maquinas
A5: 294 | B5: SERGIO CARVALHO MENDES | C5: 2019-04-06 | D5: 2026-05-08 | E5: 2026-05-09 | F5: 187.76 | G5: 1880 | H5: 853.21 | I5: 264.46 | J5: 588.75 | K5: 150.4 | L5: Dispensa sem justa causa | M5: =IFERROR(INDEX(Funcionarios!$G$3:$G$38,MATCH($A5,Funcionarios!$A$3:$A$38,0)),"") -> Operacional | N5: =IFERROR(INDEX(Funcionarios!$C$3:$C$38,MATCH($A5,Funcionarios!$A$3:$A$38,0)),"") -> Operador de Maquinas
A6: 235 | B6: MARCIA NASCIMENTO ROCHA | C6: 2019-11-30 | D6: 2026-05-02 | E6: 2026-05-17 | F6: 214.58 | G6: 1740 | H6: 889.87 | I6: 237.65 | J6: 652.22 | K6: 139.2 | L6: Termino de Contrato | M6: =IFERROR(INDEX(Funcionarios!$G$3:$G$38,MATCH($A6,Funcionarios!$A$3:$A$38,0)),"") -> ACME_OPERACIONAL_DIARIA | N6: =IFERROR(INDEX(Funcionarios!$C$3:$C$38,MATCH($A6,Funcionarios!$A$3:$A$38,0)),"") -> Auxiliar de Producao
A7: 296 | B7: RICARDO DOS SANTOS MENDES | C7: 2021-05-12 | D7: 2026-05-07 | E7: 2026-05-22 | F7: 292.58 | G7: 2050 | H7: 1202.28 | I7: 400.73 | J7: 801.55 | K7: 164 | L7: Resc. cont. exp. antec. empregador | M7: =IFERROR(INDEX(Funcionarios!$G$3:$G$38,MATCH($A7,Funcionarios!$A$3:$A$38,0)),"") -> Administracao - Fabrica | N7: =IFERROR(INDEX(Funcionarios!$C$3:$C$38,MATCH($A7,Funcionarios!$A$3:$A$38,0)),"") -> Auxiliar Administrativo
A8: 171 | B8: CRISTINA RIBEIRO PINTO | C8: 2022-08-31 | D8: 2026-05-17 | E8: 2026-05-23 | F8: 258.07 | G8: 2360 | H8: 1641.64 | I8: 412.72 | J8: 1228.92 | K8: 188.8 | L8: Dispensa sem justa causa | M8: =IFERROR(INDEX(Funcionarios!$G$3:$G$38,MATCH($A8,Funcionarios!$A$3:$A$38,0)),"") -> Operacional | N8: =IFERROR(INDEX(Funcionarios!$C$3:$C$38,MATCH($A8,Funcionarios!$A$3:$A$38,0)),"") -> Operador de Maquinas

Sheet Rubricas_Folha
A1: ACME - Rubricas da Folha
A2: Departamento_Num | B2: Departamento | C2: Rubrica_Num | D2: Rubrica_Nome | E2: Tipo | F2: N_Empregados | G2: Valor_Informado | H2: Valor_Calculado | I2: Tipo Folha
A3: 1 | B3: Administracao - Fabrica | C3: 1 | D3: HORAS NORMAIS | E3: Provento | F3: 6 | G3: 9851.4 | H3: 9757.51 | I3: Normal
A4: 1 | B4: Administracao - Fabrica | C4: 2 | D4: HORAS EXTRAS 50% | E4: Provento | F4: 6 | G4: 757.8 | H4: 746.25 | I4: Normal
A5: 1 | B5: Administracao - Fabrica | C5: 3 | D5: ADICIONAL NOTURNO | E5: Provento | F5: 6 | G5: 378.9 | H5: 362.02 | I5: Normal
A6: 1 | B6: Administracao - Fabrica | C6: 4 | D6: DSR SOBRE HORAS EXTRAS | E6: Provento | F6: 6 | G6: 252.6 | H6: 243.25 | I6: Normal
A7: 1 | B7: Administracao - Fabrica | C7: 5 | D7: INSS | E7: Desconto | F7: 6 | G7: 1136.7 | H7: 1087.9 | I7: Normal
A8: 1 | B8: Administracao - Fabrica | C8: 6 | D8: IRRF | E8: Desconto | F8: 6 | G8: 505.2 | H8: 517.37 | I8: Normal
A9: 1 | B9: Administracao - Fabrica | C9: 7 | D9: VALE TRANSPORTE | E9: Desconto | F9: 6 | G9: 252.6 | H9: 246.43 | I9: Normal
A10: 1 | B10: Administracao - Fabrica | C10: 8 | D10: VALE ALIMENTACAO | E10: Desconto | F10: 6 | G10: 189.45 | H10: 183.07 | I10: Normal
A11: 1 | B11: Administracao - Fabrica | C11: 2 | D11: HORAS EXTRAS 50% | E11: Provento | F11: 6 | G11: 90.94 | H11: 87.16 | I11: Extra
A12: 1 | B12: Administracao - Fabrica | C12: 3 | D12: ADICIONAL NOTURNO | E12: Provento | F12: 6 | G12: 45.47 | H12: 47.02 | I12: Extra
A13: 1 | B13: Administracao - Fabrica | C13: 5 | D13: INSS | E13: Desconto | F13: 6 | G13: 136.4 | H13: 141.45 | I13: Extra
A14: 1 | B14: Administracao - Fabrica | C14: 6 | D14: IRRF | E14: Desconto | F14: 6 | G14: 60.62 | H14: 61.65 | I14: Extra
... A128: 9 | B128: Administracao - Escritorio | C128: 8 | D128: VALE ALIMENTACAO | E128: Desconto | F128: 1 | G128: 4.12 | H128: 4.31 | I128: Extra

Sheet Resumo_Departamento
A1: ACME - Resumo por Departamento
A2: Departamento_Num | B2: Departamento | C2: Tipo Folha | D2: Total_Proventos | E2: Total_Descontos | F2: Liquido_Depto
A3: 1 | B3: Administracao - Fabrica | C3: Normal | D3: =SUMIFS(Rubricas_Folha!$H$3:$H$128,Rubricas_Folha!$B$3:$B$128,B3,Rubricas_Folha!$E$3:$E$128,"Provento",Rubricas_Folha!$I$3:$I$128,C3) -> 11109.03 | E3: =SUMIFS(Rubricas_Folha!$H$3:$H$128,Rubricas_Folha!$B$3:$B$128,B3,Rubricas_Folha!$E$3:$E$128,"Desconto",Rubricas_Folha!$I$3:$I$128,C3) -> 2034.77 | F3: =D3-E3 -> 9074.26
A4: 1 | B4: Administracao - Fabrica | C4: Extra | D4: =SUMIFS(Rubricas_Folha!$H$3:$H$128,Rubricas_Folha!$B$3:$B$128,B4,Rubricas_Folha!$E$3:$E$128,"Provento",Rubricas_Folha!$I$3:$I$128,C4) -> 134.18 | E4: =SUMIFS(Rubricas_Folha!$H$3:$H$128,Rubricas_Folha!$B$3:$B$128,B4,Rubricas_Folha!$E$3:$E$128,"Desconto",Rubricas_Folha!$I$3:$I$128,C4) -> 254.89 | F4: =D4-E4 -> -120.71
A5: 2 | B5: Pre-Moldados | C5: Normal | D5: =SUMIFS(Rubricas_Folha!$H$3:$H$128,Rubricas_Folha!$B$3:$B$128,B5,Rubricas_Folha!$E$3:$E$128,"Provento",Rubricas_Folha!$I$3:$I$128,C5) -> 17781.13 | E5: =SUMIFS(Rubricas_Folha!$H$3:$H$128,Rubricas_Folha!$B$3:$B$128,B5,Rubricas_Folha!$E$3:$E$128,"Desconto",Rubricas_Folha!$I$3:$I$128,C5) -> 3377.61 | F5: =D5-E5 -> 14403.52
A6: 2 | B6: Pre-Moldados | C6: Extra | D6: =SUMIFS(Rubricas_Folha!$H$3:$H$128,Rubricas_Folha!$B$3:$B$128,B6,Rubricas_Folha!$E$3:$E$128,"Provento",Rubricas_Folha!$I$3:$I$128,C6) -> 219.78 | E6: =SUMIFS(Rubricas_Folha!$H$3:$H$128,Rubricas_Folha!$B$3:$B$128,B6,Rubricas_Folha!$E$3:$E$128,"Desconto",Rubricas_Folha!$I$3:$I$128,C6) -> 395.05 | F6: =D6-E6 -> -175.27
A7: 3 | B7: Operacional | C7: Normal | D7: =SUMIFS(Rubricas_Folha!$H$3:$H$128,Rubricas_Folha!$B$3:$B$128,B7,Rubricas_Folha!$E$3:$E$128,"Provento",Rubricas_Folha!$I$3:$I$128,C7) -> 10787.76 | E7: =SUMIFS(Rubricas_Folha!$H$3:$H$128,Rubricas_Folha!$B$3:$B$128,B7,Rubricas_Folha!$E$3:$E$128,"Desconto",Rubricas_Folha!$I$3:$I$128,C7) -> 1928.94 | F7: =D7-E7 -> 8858.82
A8: 3 | B8: Operacional | C8: Extra | D8: =SUMIFS(Rubricas_Folha!$H$3:$H$128,Rubricas_Folha!$B$3:$B$128,B8,Rubricas_Folha!$E$3:$E$128,"Provento",Rubricas_Folha!$I$3:$I$128,C8) -> 125.23 | E8: =SUMIFS(Rubricas_Folha!$H$3:$H$128,Rubricas_Folha!$B$3:$B$128,B8,Rubricas_Folha!$E$3:$E$128,"Desconto",Rubricas_Folha!$I$3:$I$128,C8) -> 236.95 | F8: =D8-E8 -> -111.72
A9: 4 | B9: ACME_OPERACIONAL_DIARIA | C9: Normal | D9: =SUMIFS(Rubricas_Folha!$H$3:$H$128,Rubricas_Folha!$B$3:$B$128,B9,Rubricas_Folha!$E$3:$E$128,"Provento",Rubricas_Folha!$I$3:$I$128,C9) -> 4723.62 | E9: =SUMIFS(Rubricas_Folha!$H$3:$H$128,Rubricas_Folha!$B$3:$B$128,B9,Rubricas_Folha!$E$3:$E$128,"Desconto",Rubricas_Folha!$I$3:$I$128,C9) -> 848.25 | F9: =D9-E9 -> 3875.37
A10: 4 | B10: ACME_OPERACIONAL_DIARIA | C10: Extra | D10: =SUMIFS(Rubricas_Folha!$H$3:$H$128,Rubricas_Folha!$B$3:$B$128,B10,Rubricas_Folha!$E$3:$E$128,"Provento",Rubricas_Folha!$I$3:$I$128,C10) -> 57.06 | E10: =SUMIFS(Rubricas_Folha!$H$3:$H$128,Rubricas_Folha!$B$3:$B$128,B10,Rubricas_Folha!$E$3:$E$128,"Desconto",Rubricas_Folha!$I$3:$I$128,C10) -> 101.44 | F10: =D10-E10 -> -44.38
A11: 5 | B11: ACME_ADM DA FABRICA | C11: Normal | D11: =SUMIFS(Rubricas_Folha!$H$3:$H$128,Rubricas_Folha!$B$3:$B$128,B11,Rubricas_Folha!$E$3:$E$128,"Provento",Rubricas_Folha!$I$3:$I$128,C11) -> 30690.51 | E11: =SUMIFS(Rubricas_Folha!$H$3:$H$128,Rubricas_Folha!$B$3:$B$128,B11,Rubricas_Folha!$E$3:$E$128,"Desconto",Rubricas_Folha!$I$3:$I$128,C11) -> 5654.06 | F11: =D11-E11 -> 25036.45
A12: 5 | B12: ACME_ADM DA FABRICA | C12: Extra | D12: =SUMIFS(Rubricas_Folha!$H$3:$H$128,Rubricas_Folha!$B$3:$B$128,B12,Rubricas_Folha!$E$3:$E$128,"Provento",Rubricas_Folha!$I$3:$I$128,C12) -> 371.42 | E12: =SUMIFS(Rubricas_Folha!$H$3:$H$128,Rubricas_Folha!$B$3:$B$128,B12,Rubricas_Folha!$E$3:$E$128,"Desconto",Rubricas_Folha!$I$3:$I$128,C12) -> 673.21 | F12: =D12-E12 -> -301.79
A13: 6 | B13: Apoio a Producao | C13: Normal | D13: =SUMIFS(Rubricas_Folha!$H$3:$H$128,Rubricas_Folha!$B$3:$B$128,B13,Rubricas_Folha!$E$3:$E$128,"Provento",Rubricas_Folha!$I$3:$I$128,C13) -> 5164.48 | E13: =SUMIFS(Rubricas_Folha!$H$3:$H$128,Rubricas_Folha!$B$3:$B$128,B13,Rubricas_Folha!$E$3:$E$128,"Desconto",Rubricas_Folha!$I$3:$I$128,C13) -> 1000.21 | F13: =D13-E13 -> 4164.27
A14: 6 | B14: Apoio a Producao | C14: Extra | D14: =SUMIFS(Rubricas_Folha!$H$3:$H$128,Rubricas_Folha!$B$3:$B$128,B14,Rubricas_Folha!$E$3:$E$128,"Provento",Rubricas_Folha!$I$3:$I$128,C14) -> 63.74 | E14: =SUMIFS(Rubricas_Folha!$H$3:$H$128,Rubricas_Folha!$B$3:$B$128,B14,Rubricas_Folha!$E$3:$E$128,"Desconto",Rubricas_Folha!$I$3:$I$128,C14) -> 121.58 | F14: =D14-E14 -> -57.84
... A20: 9 | B20: Administracao - Escritorio | C20: Extra | D20: =SUMIFS(Rubricas_Folha!$H$3:$H$128,Rubricas_Folha!$B$3:$B$128,B20,Rubricas_Folha!$E$3:$E$128,"Provento",Rubricas_Folha!$I$3:$I$128,C20) -> 25.88 | E20: =SUMIFS(Rubricas_Folha!$H$3:$H$128,Rubricas_Folha!$B$3:$B$128,B20,Rubricas_Folha!$E$3:$E$128,"Desconto",Rubricas_Folha!$I$3:$I$128,C20) -> 44.47 | F20: =D20-E20 -> -18.59

Sheet Resumo_Geral
A1: Resumo Geral - Folha de Pagamento (Competencia 05/2026)
A3: Indicador | B3: Valor | C3: Observacao
A4: Total Liquido Geral (Resumo_Departamento) | B4: =SUM(Resumo_Departamento!F3:F20) -> 72043.64 | C4: Soma de Liquido_Depto (todas as folhas Normal+Extra), fonte: Resumo Mensal GERAL
A5: Total Liquido Geral (Liquidos - Normal Principal+Quinzena+Extra) | B5: =SUM(Liquidos!E3:E86) -> 103244.01 | C5: Soma de Valor pago em Liquidos (3 relatorios de liquidos)
A6: Total de Funcionarios Ativos | B6: =COUNTA(Funcionarios!A3:A38) -> 36 | C6: Contagem de linhas em Funcionarios (Relacao de Empregados)
A7: Total Horas Extras (horas) | B7: =SUM(Horas_Extras!I3:I32) -> 339.21 | C7: Soma da coluna Horas em Horas_Extras (folhas Normal+Extra)
A8: Total Horas Extras (R$ calculado) | B8: =SUM(Horas_Extras!H3:H32) -> 6653.62 | C8: Soma da coluna Valor_Calculado em Horas_Extras
A9: Total Faltas (horas) | B9: =SUM(Faltas!D3:D38) -> 43.22 | C9: Soma de Ausencias_h em Faltas (RELACAO DE FALTAS)
A10: Total Atestados (horas) | B10: =SUM(Atestados!D3:D38) -> 102.44 | C10: Soma de Ausencias_h em Atestados (RELACAO DE ATESTADOS)
A11: Total Rescisoes (R$ Liquido) | B11: =SUM(Rescisoes!J3:J8) -> 5752.79 | C11: Soma de Liquido em Rescisoes
A13: Total Liquido por Departamento (Normal + Extra)
A14: Departamento | B14: Liquido Total
A15: Administracao - Fabrica | B15: =SUMIFS(Resumo_Departamento!$F$3:$F$20,Resumo_Departamento!$B$3:$B$20,A15) -> 8953.55
A16: Pre-Moldados | B16: =SUMIFS(Resumo_Departamento!$F$3:$F$20,Resumo_Departamento!$B$3:$B$20,A16) -> 14228.25
A17: Operacional | B17: =SUMIFS(Resumo_Departamento!$F$3:$F$20,Resumo_Departamento!$B$3:$B$20,A17) -> 8747.1
A18: ACME_OPERACIONAL_DIARIA | B18: =SUMIFS(Resumo_Departamento!$F$3:$F$20,Resumo_Departamento!$B$3:$B$20,A18) -> 3830.99
A19: ACME_ADM DA FABRICA | B19: =SUMIFS(Resumo_Departamento!$F$3:$F$20,Resumo_Departamento!$B$3:$B$20,A19) -> 24734.66
A20: Apoio a Producao | B20: =SUMIFS(Resumo_Departamento!$F$3:$F$20,Resumo_Departamento!$B$3:$B$20,A20) -> 4106.43
A21: ACME_DP/RH | B21: =SUMIFS(Resumo_Departamento!$F$3:$F$20,Resumo_Departamento!$B$3:$B$20,A21) -> 3644.86
A22: ACME_PRODUCAO | B22: =SUMIFS(Resumo_Departamento!$F$3:$F$20,Resumo_Departamento!$B$3:$B$20,A22) -> 2124.27
A23: Administracao - Escritorio | B23: =SUMIFS(Resumo_Departamento!$F$3:$F$20,Resumo_Departamento!$B$3:$B$20,A23) -> 1673.53
